[{"colors":"#4a5576","id":58935170,"geo":"MA"},{"colors":"#545562","id":28616374,"geo":"MA"},{"colors":"#9b8f8a","id":51867157,"geo":"MA"},{"colors":"#3c3439","id":88317871,"geo":"MA"},{"colors":"#f36242","id":88317887,"geo":"MA"},{"colors":"#15222b","id":138242919,"geo":"MA"},{"colors":"#615d62","id":118792837,"geo":"MA"},{"colors":"#40494a","id":126308562,"geo":"MA"},{"colors":"#848388","id":138253273,"geo":"MA"},{"colors":"#96a8e3","id":30494575,"geo":"MA"},{"colors":"#87848b","id":139192999,"geo":"MA"},{"colors":"#726869","id":138130277,"geo":"MA"},{"colors":"#747673","id":140116779,"geo":"MA"},{"colors":"#8b6366","id":152124960,"geo":"MA"},{"colors":"#8e6561","id":140116783,"geo":"MA"},{"colors":"#7b656b","id":154946138,"geo":"MA"},{"colors":"#75687e","id":142863948,"geo":"MA"},{"colors":"#ac9f97","id":162567535,"geo":"MA"},{"colors":"#a9a18c","id":141625998,"geo":"MA"},{"colors":"#5e5258","id":155111347,"geo":"MA"},{"colors":"#828888","id":165959230,"geo":"MA"},{"colors":"#6a6b70","id":163030005,"geo":"MA"},{"colors":"#817970","id":180645088,"geo":"MA"},{"colors":"#635759","id":155184121,"geo":"MA"},{"colors":"#938f95","id":182026405,"geo":"MA"},{"colors":"#939695","id":175108158,"geo":"MA"},{"colors":"#5f696c","id":184350146,"geo":"MA"},{"colors":"#8c7580","id":180905140,"geo":"MA"},{"colors":"#908a91","id":186908632,"geo":"MA"},{"colors":"#585c5e","id":209242508,"geo":"MA"},{"colors":"#554853","id":201630554,"geo":"MA"},{"colors":"#7a7772","id":203847771,"geo":"MA"},{"colors":"#837986","id":192284271,"geo":"MA"},{"colors":"#777877","id":199911974,"geo":"MA"},{"colors":"#796d8a","id":216906002,"geo":"MA"},{"colors":"#604146","id":218541742,"geo":"MA"},{"colors":"#c1a993","id":217608176,"geo":"MA"},{"colors":"#a1989a","id":247622906,"geo":"MA"},{"colors":"#ae9e96","id":198966330,"geo":"MA"},{"colors":"#52555d","id":237880002,"geo":"MA"},{"colors":"#646166","id":235994414,"geo":"MA"},{"colors":"#465654","id":237049844,"geo":"MA"},{"colors":"#899dc5","id":217711569,"geo":"MA"},{"colors":"#81787a","id":247352934,"geo":"MA"},{"colors":"#446379","id":247768411,"geo":"MA"},{"colors":"#4d4e49","id":251661370,"geo":"MA"},{"colors":"#747775","id":253253829,"geo":"MA"},{"colors":"#403640","id":250863597,"geo":"MA"},{"colors":"#8c6a71","id":267934600,"geo":"MA"},{"colors":"#595c72","id":257116527,"geo":"MA"},{"colors":"#696d71","id":250551214,"geo":"MA"},{"colors":"#585970","id":263470482,"geo":"MA"},{"colors":"#aaa4a4","id":270511520,"geo":"MA"},{"colors":"#676462","id":267948744,"geo":"MA"},{"colors":"#131725","id":270221079,"geo":"MA"},{"colors":"#777974","id":260152703,"geo":"MA"},{"colors":"#887d89","id":267934625,"geo":"MA"},{"colors":"#afa196","id":270718713,"geo":"MA"},{"colors":"#96908e","id":268716080,"geo":"MA"},{"colors":"#636153","id":270522763,"geo":"MA"},{"colors":"#856a6b","id":270373846,"geo":"MA"},{"colors":"#79767a","id":270751193,"geo":"MA"},{"colors":"#756e76","id":268716076,"geo":"MA"},{"colors":"#4e514b","id":287904813,"geo":"MA"},{"colors":"#87837c","id":278986226,"geo":"MA"},{"colors":"#8c8a86","id":301185022,"geo":"MA"},{"colors":"#4a5844","id":302359412,"geo":"MA"},{"colors":"#827f83","id":303956549,"geo":"MA"},{"colors":"#6e7760","id":308288029,"geo":"MA"},{"colors":"#5b5c5f","id":306292423,"geo":"MA"},{"colors":"#9b998f","id":307879604,"geo":"MA"},{"colors":"#7a7377","id":309667860,"geo":"MA"},{"colors":"#7b7a79","id":310172291,"geo":"MA"},{"colors":"#6f738b","id":309740435,"geo":"MA"},{"colors":"#73767a","id":311117458,"geo":"MA"},{"colors":"#b5b1ad","id":310530713,"geo":"MA"},{"colors":"#8f8c83","id":311117459,"geo":"MA"},{"colors":"#b6ab98","id":310604413,"geo":"MA"},{"colors":"#7e7e83","id":304524699,"geo":"MA"},{"colors":"#797676","id":277373872,"geo":"MA"},{"colors":"#3a4b7e","id":311682750,"geo":"MA"},{"colors":"#7c7887","id":311817244,"geo":"MA"},{"colors":"#4e5b6a","id":311682755,"geo":"MA"},{"colors":"#998e8e","id":312351661,"geo":"MA"},{"colors":"#99a5ca","id":309848256,"geo":"MA"},{"colors":"#77786a","id":311484496,"geo":"MA"},{"colors":"#6b6b71","id":311669219,"geo":"MA"},{"colors":"#513537","id":310427465,"geo":"MA"},{"colors":"#435158","id":312667154,"geo":"MA"},{"colors":"#52566d","id":312865735,"geo":"MA"},{"colors":"#968c86","id":311686778,"geo":"MA"},{"colors":"#7a5565","id":312983698,"geo":"MA"},{"colors":"#846e6d","id":324111885,"geo":"MA"},{"colors":"#a0917f","id":312865731,"geo":"MA"},{"colors":"#787775","id":312529294,"geo":"MA"},{"colors":"#4b666a","id":324617482,"geo":"MA"},{"colors":"#362d39","id":325121073,"geo":"MA"},{"colors":"#867372","id":325045298,"geo":"MA"},{"colors":"#394888","id":342248319,"geo":"MA"},{"colors":"#a2a19c","id":334353871,"geo":"MA"},{"colors":"#6b6b6f","id":335727325,"geo":"MA"},{"colors":"#91888d","id":352074698,"geo":"MA"},{"colors":"#72858b","id":373531450,"geo":"MA"},{"colors":"#5d5759","id":365691394,"geo":"MA"},{"colors":"#5c5c65","id":352877751,"geo":"MA"},{"colors":"#8f8b8c","id":375651531,"geo":"MA"},{"colors":"#918e8f","id":344208785,"geo":"MA"},{"colors":"#7c7a7e","id":324616687,"geo":"MA"},{"colors":"#86868c","id":375532468,"geo":"MA"},{"colors":"#4f4f4f","id":334167646,"geo":"MA"},{"colors":"#677074","id":381792796,"geo":"MA"},{"colors":"#888691","id":405748474,"geo":"MA"},{"colors":"#5c584d","id":357007112,"geo":"MA"},{"colors":"#616774","id":414241791,"geo":"MA"},{"colors":"#4c5258","id":419266288,"geo":"MA"},{"colors":"#858067","id":427077070,"geo":"MA"},{"colors":"#6a5a53","id":427206750,"geo":"MA"},{"colors":"#9c949e","id":422985512,"geo":"MA"},{"colors":"#928d7f","id":428175071,"geo":"MA"},{"colors":"#797c7a","id":428129843,"geo":"MA"},{"colors":"#575055","id":384669910,"geo":"MA"},{"colors":"#919486","id":428185299,"geo":"MA"},{"colors":"#aab4ca","id":422850725,"geo":"MA"},{"colors":"#85868c","id":429914428,"geo":"MA"},{"colors":"#bcbcbc","id":430149383,"geo":"MA"},{"colors":"#958b84","id":429930521,"geo":"MA"},{"colors":"#97989c","id":422617918,"geo":"MA"},{"colors":"#a29a94","id":430440374,"geo":"MA"},{"colors":"#766f71","id":433870152,"geo":"MA"},{"colors":"#789bb6","id":28616512,"geo":"MA"},{"colors":"#907975","id":429780633,"geo":"MA"},{"colors":"#707c70","id":430149661,"geo":"MA"},{"colors":"#cab6b1","id":29078562,"geo":"MA"},{"colors":"#33445a","id":29907289,"geo":"MA"},{"colors":"#899b87","id":39661830,"geo":"MA"},{"colors":"#616785","id":29844227,"geo":"MA"},{"colors":"#a68887","id":29923189,"geo":"MA"},{"colors":"#979d94","id":33468154,"geo":"MA"},{"colors":"#d19f9d","id":31090677,"geo":"MA"},{"colors":"#5b694c","id":43006642,"geo":"MA"},{"colors":"#88848c","id":397748131,"geo":"MA"},{"colors":"#79a6bd","id":50733254,"geo":"MA"},{"colors":"#bbc3c8","id":43240858,"geo":"MA"},{"colors":"#86a273","id":40666619,"geo":"MA"},{"colors":"#899aa9","id":43495988,"geo":"MA"},{"colors":"#a9aa96","id":43196719,"geo":"MA"},{"colors":"#a9ada6","id":29821832,"geo":"MA"},{"colors":"#82726e","id":54911900,"geo":"MA"},{"colors":"#68b392","id":68303523,"geo":"MA"},{"colors":"#605a65","id":55553493,"geo":"MA"},{"colors":"#92a98c","id":75112376,"geo":"MA"},{"colors":"#ba7771","id":53027338,"geo":"MA"},{"colors":"#4e7da0","id":80360577,"geo":"MA"},{"colors":"#7e7d80","id":80393832,"geo":"MA"},{"colors":"#97968f","id":80425052,"geo":"MA"},{"colors":"#a39b8c","id":80429319,"geo":"MA"},{"colors":"#73a07b","id":75801530,"geo":"MA"},{"colors":"#aca8a1","id":52303794,"geo":"MA"},{"colors":"#547c8b","id":80489073,"geo":"MA"},{"colors":"#6d7070","id":80489406,"geo":"MA"},{"colors":"#919384","id":32606644,"geo":"MA"},{"colors":"#9e9792","id":80541084,"geo":"MA"},{"colors":"#7a7072","id":76796613,"geo":"MA"},{"colors":"#b2a69e","id":52387783,"geo":"MA"},{"colors":"#b6bbbb","id":79765080,"geo":"MA"},{"colors":"#485848","id":79763812,"geo":"MA"},{"colors":"#abb2b1","id":81048840,"geo":"MA"},{"colors":"#bcd0f1","id":80797792,"geo":"MA"},{"colors":"#2d415e","id":80675263,"geo":"MA"},{"colors":"#c3afa5","id":81160739,"geo":"MA"},{"colors":"#9c9792","id":431240628,"geo":"MA"},{"colors":"#a1a489","id":80870299,"geo":"MA"},{"colors":"#7a797f","id":82144222,"geo":"MA"},{"colors":"#ac7a74","id":81670741,"geo":"MA"},{"colors":"#b6927a","id":82159455,"geo":"MA"},{"colors":"#acaf9d","id":82576300,"geo":"MA"},{"colors":"#7ea1b3","id":82249768,"geo":"MA"},{"colors":"#979691","id":83143802,"geo":"MA"},{"colors":"#a5aa91","id":83327124,"geo":"MA"},{"colors":"#566c7a","id":83441151,"geo":"MA"},{"colors":"#aaa88d","id":85400123,"geo":"MA"},{"colors":"#8d7a73","id":88615747,"geo":"MA"},{"colors":"#a9a197","id":88626022,"geo":"MA"},{"colors":"#645e5d","id":88615737,"geo":"MA"},{"colors":"#9ea0a0","id":83331736,"geo":"MA"},{"colors":"#aaabaa","id":88969909,"geo":"MA"},{"colors":"#485a5b","id":87215870,"geo":"MA"},{"colors":"#8a8c90","id":89289377,"geo":"MA"},{"colors":"#4b5d6d","id":89289425,"geo":"MA"},{"colors":"#697784","id":80675155,"geo":"MA"},{"colors":"#6096a7","id":88969943,"geo":"MA"},{"colors":"#606469","id":89528963,"geo":"MA"},{"colors":"#a1a191","id":85362994,"geo":"MA"},{"colors":"#678190","id":89489548,"geo":"MA"},{"colors":"#9e9493","id":93160944,"geo":"MA"},{"colors":"#919450","id":92798895,"geo":"MA"},{"colors":"#3d9a93","id":93544300,"geo":"MA"},{"colors":"#669b78","id":93542689,"geo":"MA"},{"colors":"#c1ae9a","id":94031667,"geo":"MA"},{"colors":"#b1aeae","id":93627299,"geo":"MA"},{"colors":"#7da5ae","id":94509760,"geo":"MA"},{"colors":"#7e7474","id":96744488,"geo":"MA"},{"colors":"#7f7974","id":96744594,"geo":"MA"},{"colors":"#6f8c94","id":82159460,"geo":"MA"},{"colors":"#7a6640","id":96744489,"geo":"MA"},{"colors":"#8d9693","id":95345705,"geo":"MA"},{"colors":"#915f61","id":96744599,"geo":"MA"},{"colors":"#999891","id":101674280,"geo":"MA"},{"colors":"#6c6d64","id":100227221,"geo":"MA"},{"colors":"#7f797a","id":96744630,"geo":"MA"},{"colors":"#818254","id":102509936,"geo":"MA"},{"colors":"#b2a39a","id":115574980,"geo":"MA"},{"colors":"#857d62","id":105992529,"geo":"MA"},{"colors":"#829a89","id":110376576,"geo":"MA"},{"colors":"#484d53","id":101980259,"geo":"MA"},{"colors":"#3e8595","id":107298687,"geo":"MA"},{"colors":"#ac847f","id":105954157,"geo":"MA"},{"colors":"#a59e9f","id":116290964,"geo":"MA"},{"colors":"#9a9794","id":110890504,"geo":"MA"},{"colors":"#9a9b8f","id":115576684,"geo":"MA"},{"colors":"#9ca3a2","id":117720793,"geo":"MA"},{"colors":"#9b6d68","id":129896749,"geo":"MA"},{"colors":"#95918e","id":134321033,"geo":"MA"},{"colors":"#8b9b90","id":98649650,"geo":"MA"},{"colors":"#74a784","id":115572489,"geo":"MA"},{"colors":"#a39894","id":119324309,"geo":"MA"},{"colors":"#9f9790","id":123078934,"geo":"MA"},{"colors":"#727769","id":134399788,"geo":"MA"},{"colors":"#7f8187","id":134327724,"geo":"MA"},{"colors":"#b7b4ae","id":134302617,"geo":"MA"},{"colors":"#616c55","id":134327729,"geo":"MA"},{"colors":"#6e6a71","id":134901576,"geo":"MA"},{"colors":"#aaaaa4","id":135456221,"geo":"MA"},{"colors":"#6484a5","id":134718621,"geo":"MA"},{"colors":"#ada9a3","id":134321034,"geo":"MA"},{"colors":"#ae8579","id":134703345,"geo":"MA"},{"colors":"#5d7a8b","id":115578141,"geo":"MA"},{"colors":"#636066","id":136147900,"geo":"MA"},{"colors":"#6eaa70","id":136694842,"geo":"MA"},{"colors":"#8e959d","id":136253410,"geo":"MA"},{"colors":"#343f3a","id":136215392,"geo":"MA"},{"colors":"#b1ba9f","id":136694362,"geo":"MA"},{"colors":"#6988ac","id":137769709,"geo":"MA"},{"colors":"#929592","id":138059889,"geo":"MA"},{"colors":"#2d3537","id":135624183,"geo":"MA"},{"colors":"#8e8485","id":139634214,"geo":"MA"},{"colors":"#3b4048","id":144812158,"geo":"MA"},{"colors":"#606976","id":134473440,"geo":"MA"},{"colors":"#959499","id":140469367,"geo":"MA"},{"colors":"#818b72","id":143727082,"geo":"MA"},{"colors":"#8c716a","id":146993254,"geo":"MA"},{"colors":"#9d9894","id":139634204,"geo":"MA"},{"colors":"#9a9590","id":145642894,"geo":"MA"},{"colors":"#4f4f45","id":157339737,"geo":"MA"},{"colors":"#b18a88","id":155081084,"geo":"MA"},{"colors":"#736973","id":152242273,"geo":"MA"},{"colors":"#b1adac","id":158892408,"geo":"MA"},{"colors":"#948f83","id":151182340,"geo":"MA"},{"colors":"#a97878","id":161837223,"geo":"MA"},{"colors":"#777a62","id":149084410,"geo":"MA"},{"colors":"#bcc3ca","id":167007939,"geo":"MA"},{"colors":"#777479","id":165261621,"geo":"MA"},{"colors":"#90b3a0","id":157479128,"geo":"MA"},{"colors":"#555d74","id":163147157,"geo":"MA"},{"colors":"#c58c82","id":164772547,"geo":"MA"},{"colors":"#73766d","id":172760739,"geo":"MA"},{"colors":"#0f1a37","id":175112479,"geo":"MA"},{"colors":"#afab9b","id":185698253,"geo":"MA"},{"colors":"#7e7e86","id":186509639,"geo":"MA"},{"colors":"#424e3a","id":186833548,"geo":"MA"},{"colors":"#686e73","id":186941530,"geo":"MA"},{"colors":"#6793af","id":174863592,"geo":"MA"},{"colors":"#b39782","id":172029036,"geo":"MA"},{"colors":"#b1b1aa","id":185651868,"geo":"MA"},{"colors":"#33332e","id":199422165,"geo":"MA"},{"colors":"#aea293","id":195819521,"geo":"MA"},{"colors":"#9a9a8e","id":203019564,"geo":"MA"},{"colors":"#525d4f","id":186986555,"geo":"MA"},{"colors":"#8aa995","id":204494922,"geo":"MA"},{"colors":"#3a4a4e","id":188162183,"geo":"MA"},{"colors":"#37303a","id":206189215,"geo":"MA"},{"colors":"#9a9799","id":203960350,"geo":"MA"},{"colors":"#394247","id":202360869,"geo":"MA"},{"colors":"#969491","id":214297487,"geo":"MA"},{"colors":"#6c7766","id":218331037,"geo":"MA"},{"colors":"#3d4c50","id":219471135,"geo":"MA"},{"colors":"#938b85","id":229435473,"geo":"MA"},{"colors":"#d2c9bd","id":224185119,"geo":"MA"},{"colors":"#b1987d","id":219155260,"geo":"MA"},{"colors":"#59584f","id":230756983,"geo":"MA"},{"colors":"#907f86","id":234150509,"geo":"MA"},{"colors":"#757978","id":234940743,"geo":"MA"},{"colors":"#9f8e80","id":219426267,"geo":"MA"},{"colors":"#898584","id":234940782,"geo":"MA"},{"colors":"#898886","id":237467957,"geo":"MA"},{"colors":"#959493","id":234939922,"geo":"MA"},{"colors":"#83aab0","id":226926797,"geo":"MA"},{"colors":"#5a8aac","id":243011694,"geo":"MA"},{"colors":"#818071","id":246063655,"geo":"MA"},{"colors":"#9d918e","id":244762432,"geo":"MA"},{"colors":"#a9a196","id":248179588,"geo":"MA"},{"colors":"#a4a3a4","id":244770473,"geo":"MA"},{"colors":"#3d5a6f","id":245220030,"geo":"MA"},{"colors":"#5175ae","id":249617978,"geo":"MA"},{"colors":"#3e6292","id":249914512,"geo":"MA"},{"colors":"#3a434b","id":242754213,"geo":"MA"},{"colors":"#545950","id":249852939,"geo":"MA"},{"colors":"#64656f","id":248442422,"geo":"MA"},{"colors":"#968f8d","id":250246669,"geo":"MA"},{"colors":"#909184","id":250124833,"geo":"MA"},{"colors":"#80986c","id":250061071,"geo":"MA"},{"colors":"#2a4857","id":250005842,"geo":"MA"},{"colors":"#766d60","id":250462325,"geo":"MA"},{"colors":"#94858b","id":250550999,"geo":"MA"},{"colors":"#6e7057","id":250258660,"geo":"MA"},{"colors":"#45536c","id":252283984,"geo":"MA"},{"colors":"#8f6e6e","id":250896098,"geo":"MA"},{"colors":"#666865","id":251779429,"geo":"MA"},{"colors":"#a49184","id":249836129,"geo":"MA"},{"colors":"#3f404e","id":257527197,"geo":"MA"},{"colors":"#82847f","id":257124454,"geo":"MA"},{"colors":"#2c2928","id":252078574,"geo":"MA"},{"colors":"#aea9ab","id":255736397,"geo":"MA"},{"colors":"#929d97","id":264546396,"geo":"MA"},{"colors":"#95a58b","id":264546392,"geo":"MA"},{"colors":"#84a9a1","id":266855561,"geo":"MA"},{"colors":"#4b435a","id":257480578,"geo":"MA"},{"colors":"#6d7b46","id":266954975,"geo":"MA"},{"colors":"#b9baae","id":264546388,"geo":"MA"},{"colors":"#aca8a0","id":267106853,"geo":"MA"},{"colors":"#1e3b41","id":267934603,"geo":"MA"},{"colors":"#69749a","id":434300577,"geo":"MA"},{"colors":"#639c8e","id":270924554,"geo":"MA"},{"colors":"#869a89","id":281421956,"geo":"MA"},{"colors":"#9a9898","id":283894171,"geo":"MA"},{"colors":"#5a5c72","id":268716007,"geo":"MA"},{"colors":"#afa28c","id":285602359,"geo":"MA"},{"colors":"#6e737a","id":287130962,"geo":"MA"},{"colors":"#898e7e","id":273632759,"geo":"MA"},{"colors":"#5e6a5d","id":284554227,"geo":"MA"},{"colors":"#94a8ab","id":287384436,"geo":"MA"},{"colors":"#848975","id":288858108,"geo":"MA"},{"colors":"#909c8e","id":289489082,"geo":"MA"},{"colors":"#c4bcaa","id":302426667,"geo":"MA"},{"colors":"#84908a","id":288139956,"geo":"MA"},{"colors":"#8e877d","id":293137023,"geo":"MA"},{"colors":"#98a27c","id":290230321,"geo":"MA"},{"colors":"#898160","id":304321077,"geo":"MA"},{"colors":"#676b79","id":305333592,"geo":"MA"},{"colors":"#818086","id":306068912,"geo":"MA"},{"colors":"#9f9b99","id":295041912,"geo":"MA"},{"colors":"#aaa9ad","id":303562830,"geo":"MA"},{"colors":"#9998a0","id":307477074,"geo":"MA"},{"colors":"#46575d","id":307312632,"geo":"MA"},{"colors":"#3a4544","id":307506173,"geo":"MA"},{"colors":"#c7c5bb","id":296526399,"geo":"MA"},{"colors":"#a29a90","id":289500856,"geo":"MA"},{"colors":"#9e978d","id":307806933,"geo":"MA"},{"colors":"#beb6b5","id":306169480,"geo":"MA"},{"colors":"#5a6a60","id":309073785,"geo":"MA"},{"colors":"#abac94","id":308805986,"geo":"MA"},{"colors":"#696c66","id":309237208,"geo":"MA"},{"colors":"#afa9a2","id":308497576,"geo":"MA"},{"colors":"#d2d2c9","id":309143375,"geo":"MA"},{"colors":"#655150","id":309458738,"geo":"MA"},{"colors":"#7daa70","id":309568599,"geo":"MA"},{"colors":"#496069","id":309937256,"geo":"MA"},{"colors":"#424e4e","id":307519394,"geo":"MA"},{"colors":"#4e5c47","id":308480091,"geo":"MA"},{"colors":"#dfd1bf","id":309595830,"geo":"MA"},{"colors":"#c3afa4","id":309998239,"geo":"MA"},{"colors":"#c7bdc1","id":310004100,"geo":"MA"},{"colors":"#959993","id":310007709,"geo":"MA"},{"colors":"#616f65","id":310374272,"geo":"MA"},{"colors":"#cac4bd","id":310267682,"geo":"MA"},{"colors":"#abb4a8","id":310457409,"geo":"MA"},{"colors":"#51636f","id":310457187,"geo":"MA"},{"colors":"#28323e","id":308476667,"geo":"MA"},{"colors":"#755c54","id":310427466,"geo":"MA"},{"colors":"#a0828e","id":310745766,"geo":"MA"},{"colors":"#7ca897","id":310896561,"geo":"MA"},{"colors":"#4c85aa","id":310500926,"geo":"MA"},{"colors":"#7e8876","id":311301985,"geo":"MA"},{"colors":"#99999a","id":310745764,"geo":"MA"},{"colors":"#969b9f","id":311147978,"geo":"MA"},{"colors":"#aca293","id":311414549,"geo":"MA"},{"colors":"#1a262e","id":311676441,"geo":"MA"},{"colors":"#89958e","id":311301988,"geo":"MA"},{"colors":"#a89479","id":311301991,"geo":"MA"},{"colors":"#a6a290","id":311356055,"geo":"MA"},{"colors":"#79b4d9","id":311301984,"geo":"MA"},{"colors":"#626d49","id":311301996,"geo":"MA"},{"colors":"#a29988","id":311301998,"geo":"MA"},{"colors":"#8f8e91","id":312015161,"geo":"MA"},{"colors":"#6a676e","id":312150795,"geo":"MA"},{"colors":"#a29e97","id":312486618,"geo":"MA"},{"colors":"#4d464c","id":312531764,"geo":"MA"},{"colors":"#a19992","id":312530267,"geo":"MA"},{"colors":"#c5acab","id":311851812,"geo":"MA"},{"colors":"#556056","id":312712198,"geo":"MA"},{"colors":"#c6a292","id":310683899,"geo":"MA"},{"colors":"#566550","id":312958187,"geo":"MA"},{"colors":"#656d69","id":313033269,"geo":"MA"},{"colors":"#ba9d72","id":312458759,"geo":"MA"},{"colors":"#a5918e","id":312711814,"geo":"MA"},{"colors":"#6a776b","id":313033271,"geo":"MA"},{"colors":"#6a696c","id":312713976,"geo":"MA"},{"colors":"#82a1b7","id":312530266,"geo":"MA"},{"colors":"#bdbdb0","id":316676118,"geo":"MA"},{"colors":"#645c62","id":316890628,"geo":"MA"},{"colors":"#a8a6a5","id":312504804,"geo":"MA"},{"colors":"#434340","id":319033041,"geo":"MA"},{"colors":"#3e455d","id":318266656,"geo":"MA"},{"colors":"#797f7b","id":319632072,"geo":"MA"},{"colors":"#8ca89b","id":320013168,"geo":"MA"},{"colors":"#777567","id":317205260,"geo":"MA"},{"colors":"#6c6f73","id":318175644,"geo":"MA"},{"colors":"#c3b4b5","id":327308643,"geo":"MA"},{"colors":"#9b9ea0","id":331613162,"geo":"MA"},{"colors":"#497471","id":327517683,"geo":"MA"},{"colors":"#7d7a63","id":346970671,"geo":"MA"},{"colors":"#5d6861","id":346972637,"geo":"MA"},{"colors":"#858187","id":339799515,"geo":"MA"},{"colors":"#b2a7a8","id":340304145,"geo":"MA"},{"colors":"#9a9a92","id":358146711,"geo":"MA"},{"colors":"#91988f","id":356187514,"geo":"MA"},{"colors":"#bfb7aa","id":375661694,"geo":"MA"},{"colors":"#b5b8ad","id":359605359,"geo":"MA"},{"colors":"#909093","id":359421290,"geo":"MA"},{"colors":"#828173","id":372398732,"geo":"MA"},{"colors":"#888b96","id":371839600,"geo":"MA"},{"colors":"#5e7684","id":370245348,"geo":"MA"},{"colors":"#8a9993","id":373164127,"geo":"MA"},{"colors":"#0c1635","id":379089718,"geo":"MA"},{"colors":"#4d4f57","id":378253048,"geo":"MA"},{"colors":"#53743f","id":377066426,"geo":"MA"},{"colors":"#3e759a","id":376015649,"geo":"MA"},{"colors":"#9a9f93","id":377066422,"geo":"MA"},{"colors":"#767f7c","id":381220352,"geo":"MA"},{"colors":"#93908f","id":385513777,"geo":"MA"},{"colors":"#aeb4a6","id":388177659,"geo":"MA"},{"colors":"#65696f","id":395395048,"geo":"MA"},{"colors":"#8c9091","id":396483253,"geo":"MA"},{"colors":"#4d5c5b","id":384686194,"geo":"MA"},{"colors":"#a29e98","id":387157471,"geo":"MA"},{"colors":"#687c75","id":377542430,"geo":"MA"},{"colors":"#7d9093","id":382678930,"geo":"MA"},{"colors":"#2f6fa0","id":395855216,"geo":"MA"},{"colors":"#52624b","id":389991191,"geo":"MA"},{"colors":"#cca8a2","id":404478201,"geo":"MA"},{"colors":"#769bb9","id":408914191,"geo":"MA"},{"colors":"#959089","id":408907222,"geo":"MA"},{"colors":"#a1a2a4","id":410374785,"geo":"MA"},{"colors":"#2a2e3e","id":414507972,"geo":"MA"},{"colors":"#8d8e95","id":399142788,"geo":"MA"},{"colors":"#7b9178","id":401862368,"geo":"MA"},{"colors":"#aba598","id":415027040,"geo":"MA"},{"colors":"#cec8b5","id":414996561,"geo":"MA"},{"colors":"#bbb3a6","id":415504019,"geo":"MA"},{"colors":"#b9b7ae","id":415529913,"geo":"MA"},{"colors":"#394950","id":417071635,"geo":"MA"},{"colors":"#8f8f87","id":412967833,"geo":"MA"},{"colors":"#b7c8c7","id":417077753,"geo":"MA"},{"colors":"#9a9687","id":417886076,"geo":"MA"},{"colors":"#667783","id":417261666,"geo":"MA"},{"colors":"#c2bcb4","id":416128962,"geo":"MA"},{"colors":"#557867","id":417072285,"geo":"MA"},{"colors":"#757874","id":417839433,"geo":"MA"},{"colors":"#949586","id":418997816,"geo":"MA"},{"colors":"#83625f","id":418316705,"geo":"MA"},{"colors":"#8c8b84","id":417839445,"geo":"MA"},{"colors":"#494e61","id":414988158,"geo":"MA"},{"colors":"#bcb9b3","id":416060511,"geo":"MA"},{"colors":"#b7bbb7","id":418997696,"geo":"MA"},{"colors":"#565d76","id":417078947,"geo":"MA"},{"colors":"#30304c","id":420814325,"geo":"MA"},{"colors":"#485c4a","id":419009259,"geo":"MA"},{"colors":"#929c8d","id":419009677,"geo":"MA"},{"colors":"#c1c2b9","id":422059139,"geo":"MA"},{"colors":"#afa495","id":420834012,"geo":"MA"},{"colors":"#787a5c","id":418998536,"geo":"MA"},{"colors":"#8e857f","id":422077616,"geo":"MA"},{"colors":"#b8a99b","id":422317257,"geo":"MA"},{"colors":"#96aea8","id":422073332,"geo":"MA"},{"colors":"#9a9190","id":422075780,"geo":"MA"},{"colors":"#88a1b8","id":422481913,"geo":"MA"},{"colors":"#88a6b8","id":423453138,"geo":"MA"},{"colors":"#7ca7c0","id":423454355,"geo":"MA"},{"colors":"#767473","id":422940762,"geo":"MA"},{"colors":"#5a5758","id":199730203,"geo":"MA"},{"colors":"#919684","id":186986556,"geo":"MA"},{"colors":"#626b5f","id":260173043,"geo":"MA"},{"colors":"#565a4c","id":311028834,"geo":"MA"},{"colors":"#363a34","id":308291061,"geo":"MA"},{"colors":"#3d382b","id":206900662,"geo":"MA"},{"colors":"#444344","id":312983699,"geo":"MA"},{"colors":"#676c60","id":321150795,"geo":"MA"},{"colors":"#77747d","id":422283887,"geo":"MA"},{"colors":"#39362f","id":354408462,"geo":"MA"},{"colors":"#47534b","id":415632044,"geo":"MA"},{"colors":"#838574","id":434805509,"geo":"MA"},{"colors":"#838283","id":438077312,"geo":"MA"},{"colors":"#717062","id":437360123,"geo":"MA"},{"colors":"#5f694e","id":445313263,"geo":"MA"},{"colors":"#7e91ae","id":445391216,"geo":"MA"},{"colors":"#955e55","id":437445333,"geo":"MA"},{"colors":"#6b7160","id":434920640,"geo":"MA"},{"colors":"#6b747c","id":436027454,"geo":"MA"},{"colors":"#938f90","id":449143235,"geo":"MA"},{"colors":"#5a6465","id":464004482,"geo":"MA"},{"colors":"#5c5a4e","id":453395786,"geo":"MA"},{"colors":"#696b83","id":442472343,"geo":"MA"},{"colors":"#566265","id":469254033,"geo":"MA"},{"colors":"#838888","id":450209991,"geo":"MA"},{"colors":"#5e605c","id":448945101,"geo":"MA"},{"colors":"#363f43","id":464005111,"geo":"MA"},{"colors":"#7d7074","id":469254019,"geo":"MA"},{"colors":"#6c6b6c","id":487171827,"geo":"MA"},{"colors":"#6f6e6e","id":498839630,"geo":"MA"},{"colors":"#545b60","id":483233738,"geo":"MA"},{"colors":"#84797e","id":500427570,"geo":"MA"},{"colors":"#777d7f","id":450689028,"geo":"MA"},{"colors":"#8b8588","id":469291829,"geo":"MA"},{"colors":"#5b6373","id":500684710,"geo":"MA"},{"colors":"#767682","id":500467100,"geo":"MA"},{"colors":"#9490a2","id":502159352,"geo":"MA"},{"colors":"#214146","id":502162282,"geo":"MA"},{"colors":"#727784","id":500468358,"geo":"MA"},{"colors":"#2d2e36","id":512077001,"geo":"MA"},{"colors":"#7e777d","id":498373071,"geo":"MA"},{"colors":"#9a7f76","id":514639385,"geo":"MA"},{"colors":"#6d779d","id":538814309,"geo":"MA"},{"colors":"#556189","id":538814297,"geo":"MA"},{"colors":"#696e75","id":541753418,"geo":"MA"},{"colors":"#828078","id":502890286,"geo":"MA"},{"colors":"#656463","id":541753867,"geo":"MA"},{"colors":"#3e4347","id":543380444,"geo":"MA"},{"colors":"#2a3250","id":544078153,"geo":"MA"},{"colors":"#606984","id":541739068,"geo":"MA"},{"colors":"#7e8082","id":545459634,"geo":"MA"},{"colors":"#758676","id":544640195,"geo":"MA"},{"colors":"#44586d","id":544268632,"geo":"MA"},{"colors":"#8ca8e0","id":541756643,"geo":"MA"},{"colors":"#7d7d84","id":552700817,"geo":"MA"},{"colors":"#62686b","id":557763179,"geo":"MA"},{"colors":"#84857f","id":578653059,"geo":"MA"},{"colors":"#b5afa8","id":572870765,"geo":"MA"},{"colors":"#86737a","id":541328869,"geo":"MA"},{"colors":"#78737c","id":578671111,"geo":"MA"},{"colors":"#8c8d95","id":573308776,"geo":"MA"},{"colors":"#94766f","id":583342172,"geo":"MA"},{"colors":"#8e7f78","id":587928714,"geo":"MA"},{"colors":"#82858e","id":598086218,"geo":"MA"},{"colors":"#4a5481","id":608084106,"geo":"MA"},{"colors":"#8f8e8f","id":592833669,"geo":"MA"},{"colors":"#8f9286","id":609829048,"geo":"MA"},{"colors":"#8893b1","id":544092004,"geo":"MA"},{"colors":"#938b86","id":596227890,"geo":"MA"},{"colors":"#494a4a","id":609827166,"geo":"MA"},{"colors":"#6b737c","id":609822219,"geo":"MA"},{"colors":"#5f5b59","id":601865415,"geo":"MA"},{"colors":"#515b60","id":622837619,"geo":"MA"},{"colors":"#7b8390","id":589146589,"geo":"MA"},{"colors":"#343c3f","id":611380909,"geo":"MA"},{"colors":"#77727a","id":640378993,"geo":"MA"},{"colors":"#343a4b","id":615871669,"geo":"MA"},{"colors":"#aea69d","id":618642823,"geo":"MA"},{"colors":"#87828a","id":653375045,"geo":"MA"},{"colors":"#837c7b","id":650097320,"geo":"MA"},{"colors":"#929cbb","id":653409976,"geo":"MA"},{"colors":"#717991","id":653408143,"geo":"MA"},{"colors":"#4d5786","id":653409974,"geo":"MA"},{"colors":"#676e72","id":672719770,"geo":"MA"},{"colors":"#555775","id":654085081,"geo":"MA"},{"colors":"#474936","id":636043742,"geo":"MA"},{"colors":"#726f75","id":653855136,"geo":"MA"},{"colors":"#3e413b","id":679084359,"geo":"MA"},{"colors":"#6e7670","id":672711413,"geo":"MA"},{"colors":"#5c7ac4","id":687785408,"geo":"MA"},{"colors":"#79555a","id":689794839,"geo":"MA"},{"colors":"#5b6f71","id":690925800,"geo":"MA"},{"colors":"#a37a77","id":667078378,"geo":"MA"},{"colors":"#9f99a0","id":693104231,"geo":"MA"},{"colors":"#817e7a","id":693944544,"geo":"MA"},{"colors":"#8e857a","id":697883752,"geo":"MA"},{"colors":"#857f88","id":700517700,"geo":"MA"},{"colors":"#334142","id":699012285,"geo":"MA"},{"colors":"#6b6b78","id":678672541,"geo":"MA"},{"colors":"#0e1321","id":697883754,"geo":"MA"},{"colors":"#584f3d","id":698252793,"geo":"MA"},{"colors":"#676579","id":700313477,"geo":"MA"},{"colors":"#5a6963","id":705654352,"geo":"MA"},{"colors":"#1f2847","id":704704367,"geo":"MA"},{"colors":"#76829b","id":726899684,"geo":"MA"},{"colors":"#767c7d","id":706512942,"geo":"MA"},{"colors":"#646870","id":710765927,"geo":"MA"},{"colors":"#a0968f","id":716830958,"geo":"MA"},{"colors":"#858787","id":744497183,"geo":"MA"},{"colors":"#2a2227","id":753532547,"geo":"MA"},{"colors":"#8c8686","id":756257173,"geo":"MA"},{"colors":"#908d8a","id":756255930,"geo":"MA"},{"colors":"#83807e","id":757718162,"geo":"MA"},{"colors":"#3c3a47","id":773066215,"geo":"MA"},{"colors":"#50535b","id":782469402,"geo":"MA"},{"colors":"#777e8a","id":753146330,"geo":"MA"},{"colors":"#6e6a69","id":784045567,"geo":"MA"},{"colors":"#586b71","id":783403777,"geo":"MA"},{"colors":"#6d6d66","id":798460401,"geo":"MA"},{"colors":"#8f7872","id":794991594,"geo":"MA"},{"colors":"#98a9ce","id":713678392,"geo":"MA"},{"colors":"#232632","id":808876800,"geo":"MA"},{"colors":"#4e5b51","id":825073821,"geo":"MA"},{"colors":"#797c73","id":817282746,"geo":"MA"},{"colors":"#8c8785","id":828421496,"geo":"MA"},{"colors":"#7f7a72","id":839518032,"geo":"MA"},{"colors":"#948689","id":826321211,"geo":"MA"},{"colors":"#677358","id":852062302,"geo":"MA"},{"colors":"#646c6e","id":852962984,"geo":"MA"},{"colors":"#717776","id":852968719,"geo":"MA"},{"colors":"#928d80","id":844687122,"geo":"MA"},{"colors":"#4f5771","id":874694052,"geo":"MA"},{"colors":"#777a8e","id":858756707,"geo":"MA"},{"colors":"#66616b","id":434837057,"geo":"MA"},{"colors":"#959086","id":875158545,"geo":"MA"},{"colors":"#897d85","id":441249692,"geo":"MA"},{"colors":"#b0bdba","id":435420041,"geo":"MA"},{"colors":"#686a7e","id":736490624,"geo":"MA"},{"colors":"#8f8e89","id":437635301,"geo":"MA"},{"colors":"#a0a09f","id":443684597,"geo":"MA"},{"colors":"#9b9480","id":439179392,"geo":"MA"},{"colors":"#9baa9e","id":444162332,"geo":"MA"},{"colors":"#665a58","id":443672423,"geo":"MA"},{"colors":"#1e232f","id":845218417,"geo":"MA"},{"colors":"#817e82","id":824432813,"geo":"MA"},{"colors":"#8c8481","id":449265095,"geo":"MA"},{"colors":"#98898a","id":455409372,"geo":"MA"},{"colors":"#5b6654","id":824718668,"geo":"MA"},{"colors":"#7b90a3","id":443684602,"geo":"MA"},{"colors":"#b7b8bc","id":466461460,"geo":"MA"},{"colors":"#9abed0","id":463136584,"geo":"MA"},{"colors":"#a4968c","id":469988691,"geo":"MA"},{"colors":"#1c2939","id":469230441,"geo":"MA"},{"colors":"#bcb9b5","id":461244017,"geo":"MA"},{"colors":"#919897","id":476414553,"geo":"MA"},{"colors":"#9bb2b7","id":469325033,"geo":"MA"},{"colors":"#769cad","id":479108151,"geo":"MA"},{"colors":"#667e76","id":474836005,"geo":"MA"},{"colors":"#848560","id":472347918,"geo":"MA"},{"colors":"#868b7e","id":752862297,"geo":"MA"},{"colors":"#a3948f","id":481127383,"geo":"MA"},{"colors":"#d4c9b0","id":470450046,"geo":"MA"},{"colors":"#afa8a2","id":484144578,"geo":"MA"},{"colors":"#b5b0ab","id":475202434,"geo":"MA"},{"colors":"#818b7c","id":447266954,"geo":"MA"},{"colors":"#a6a3a1","id":484144581,"geo":"MA"},{"colors":"#98a99b","id":488037579,"geo":"MA"},{"colors":"#a69c7c","id":480318051,"geo":"MA"},{"colors":"#8f9284","id":485935868,"geo":"MA"},{"colors":"#cdc6c3","id":490329193,"geo":"MA"},{"colors":"#7b847b","id":482885973,"geo":"MA"},{"colors":"#8c877e","id":488746496,"geo":"MA"},{"colors":"#5a7492","id":495977383,"geo":"MA"},{"colors":"#97a095","id":490599320,"geo":"MA"},{"colors":"#6376a5","id":487530659,"geo":"MA"},{"colors":"#a9a896","id":493478418,"geo":"MA"},{"colors":"#515c61","id":499193975,"geo":"MA"},{"colors":"#5a635c","id":491025841,"geo":"MA"},{"colors":"#6c757e","id":502147405,"geo":"MA"},{"colors":"#65616b","id":500452036,"geo":"MA"},{"colors":"#74727f","id":500696167,"geo":"MA"},{"colors":"#6d6b68","id":504559333,"geo":"MA"},{"colors":"#393f3a","id":504836490,"geo":"MA"},{"colors":"#8aa18c","id":484144584,"geo":"MA"},{"colors":"#47404b","id":508502722,"geo":"MA"},{"colors":"#536f68","id":504852112,"geo":"MA"},{"colors":"#939496","id":509654595,"geo":"MA"},{"colors":"#849d7c","id":512685923,"geo":"MA"},{"colors":"#90acbd","id":514674474,"geo":"MA"},{"colors":"#858a82","id":524269953,"geo":"MA"},{"colors":"#7da3b5","id":524973912,"geo":"MA"},{"colors":"#557b8c","id":515347652,"geo":"MA"},{"colors":"#9b989a","id":524757727,"geo":"MA"},{"colors":"#999a99","id":481124824,"geo":"MA"},{"colors":"#a2a699","id":525202373,"geo":"MA"},{"colors":"#868381","id":504852110,"geo":"MA"},{"colors":"#9fadbb","id":533472839,"geo":"MA"},{"colors":"#2d3344","id":532982945,"geo":"MA"},{"colors":"#8cadc5","id":495977377,"geo":"MA"},{"colors":"#c9c5bf","id":541737979,"geo":"MA"},{"colors":"#878481","id":541738807,"geo":"MA"},{"colors":"#b1b396","id":535349405,"geo":"MA"},{"colors":"#6b95b1","id":485616882,"geo":"MA"},{"colors":"#78827d","id":541753556,"geo":"MA"},{"colors":"#9d8f83","id":544104320,"geo":"MA"},{"colors":"#38455e","id":544269461,"geo":"MA"},{"colors":"#989497","id":534882250,"geo":"MA"},{"colors":"#99a1aa","id":544107045,"geo":"MA"},{"colors":"#acbea4","id":546934271,"geo":"MA"},{"colors":"#263239","id":546895281,"geo":"MA"},{"colors":"#707067","id":548222299,"geo":"MA"},{"colors":"#a8a5a5","id":546807015,"geo":"MA"},{"colors":"#b8b39d","id":552215401,"geo":"MA"},{"colors":"#91879b","id":560588412,"geo":"MA"},{"colors":"#ada291","id":559888935,"geo":"MA"},{"colors":"#6073b4","id":561179490,"geo":"MA"},{"colors":"#c6c5bb","id":565998346,"geo":"MA"},{"colors":"#555e51","id":562338595,"geo":"MA"},{"colors":"#b8b7a9","id":565886880,"geo":"MA"},{"colors":"#64746f","id":562625881,"geo":"MA"},{"colors":"#9e9c9f","id":567081539,"geo":"MA"},{"colors":"#616849","id":570090482,"geo":"MA"},{"colors":"#c37577","id":566003985,"geo":"MA"},{"colors":"#828d85","id":562553920,"geo":"MA"},{"colors":"#918f90","id":572858241,"geo":"MA"},{"colors":"#69798b","id":570122606,"geo":"MA"},{"colors":"#5d6c5e","id":574538260,"geo":"MA"},{"colors":"#999480","id":578234330,"geo":"MA"},{"colors":"#958f6f","id":578641652,"geo":"MA"},{"colors":"#a8a098","id":561347498,"geo":"MA"},{"colors":"#bbb5af","id":581734947,"geo":"MA"},{"colors":"#9da693","id":579438822,"geo":"MA"},{"colors":"#668c9a","id":578560993,"geo":"MA"},{"colors":"#8d8a91","id":582392752,"geo":"MA"},{"colors":"#716f7c","id":572837707,"geo":"MA"},{"colors":"#906466","id":582735320,"geo":"MA"},{"colors":"#88a8c4","id":583796234,"geo":"MA"},{"colors":"#97a19a","id":583375600,"geo":"MA"},{"colors":"#c5bbb0","id":584976648,"geo":"MA"},{"colors":"#7b7c4a","id":584922329,"geo":"MA"},{"colors":"#949395","id":585918460,"geo":"MA"},{"colors":"#666e68","id":579394746,"geo":"MA"},{"colors":"#b7b3af","id":584966876,"geo":"MA"},{"colors":"#726c5b","id":590633023,"geo":"MA"},{"colors":"#dbdedd","id":591411627,"geo":"MA"},{"colors":"#8a6458","id":592404512,"geo":"MA"},{"colors":"#bac1bf","id":594384796,"geo":"MA"},{"colors":"#5f5a52","id":544258909,"geo":"MA"},{"colors":"#9ca09f","id":594384807,"geo":"MA"},{"colors":"#707575","id":596103255,"geo":"MA"},{"colors":"#756e69","id":598363775,"geo":"MA"},{"colors":"#6d7456","id":588428334,"geo":"MA"},{"colors":"#979290","id":584979860,"geo":"MA"},{"colors":"#666c7d","id":579644436,"geo":"MA"},{"colors":"#9b9891","id":597566380,"geo":"MA"},{"colors":"#736c81","id":587791707,"geo":"MA"},{"colors":"#a6a6a2","id":599481207,"geo":"MA"},{"colors":"#66666b","id":599481204,"geo":"MA"},{"colors":"#c3c4bc","id":602679729,"geo":"MA"},{"colors":"#abd0d5","id":611880421,"geo":"MA"},{"colors":"#626e71","id":615639234,"geo":"MA"},{"colors":"#b4ae87","id":605591495,"geo":"MA"},{"colors":"#6d6d68","id":612063933,"geo":"MA"},{"colors":"#909ea3","id":620648934,"geo":"MA"},{"colors":"#504e4b","id":608079148,"geo":"MA"},{"colors":"#5e6656","id":631695054,"geo":"MA"},{"colors":"#8c8386","id":633693344,"geo":"MA"},{"colors":"#afa8a1","id":616382552,"geo":"MA"},{"colors":"#6f6d71","id":584976654,"geo":"MA"},{"colors":"#6a7f7b","id":634009479,"geo":"MA"},{"colors":"#809ca9","id":637572692,"geo":"MA"},{"colors":"#525349","id":632656552,"geo":"MA"},{"colors":"#959385","id":637572715,"geo":"MA"},{"colors":"#928f8e","id":627846417,"geo":"MA"},{"colors":"#a19b94","id":639487150,"geo":"MA"},{"colors":"#5a88a2","id":633728808,"geo":"MA"},{"colors":"#6a7386","id":643233488,"geo":"MA"},{"colors":"#2e4b5e","id":642630916,"geo":"MA"},{"colors":"#475639","id":648509298,"geo":"MA"},{"colors":"#a5a39b","id":643264960,"geo":"MA"},{"colors":"#b7b6b4","id":639105815,"geo":"MA"},{"colors":"#28212f","id":648561201,"geo":"MA"},{"colors":"#707478","id":644451289,"geo":"MA"},{"colors":"#a0adde","id":642896603,"geo":"MA"},{"colors":"#86848e","id":653409979,"geo":"MA"},{"colors":"#848984","id":653505237,"geo":"MA"},{"colors":"#26364c","id":653408148,"geo":"MA"},{"colors":"#8ab3d1","id":652558354,"geo":"MA"},{"colors":"#72735d","id":648876670,"geo":"MA"},{"colors":"#8a9a92","id":654310315,"geo":"MA"},{"colors":"#a4a299","id":644063221,"geo":"MA"},{"colors":"#8499a7","id":660310786,"geo":"MA"},{"colors":"#99b3c5","id":666943957,"geo":"MA"},{"colors":"#bab1a8","id":655281098,"geo":"MA"},{"colors":"#79776e","id":673511425,"geo":"MA"},{"colors":"#a5a6a6","id":684687938,"geo":"MA"},{"colors":"#716653","id":600820696,"geo":"MA"},{"colors":"#968f8d","id":664539892,"geo":"MA"},{"colors":"#5c5d4b","id":679493426,"geo":"MA"},{"colors":"#8e9686","id":672749886,"geo":"MA"},{"colors":"#a09b92","id":684692102,"geo":"MA"},{"colors":"#7f7c78","id":683992007,"geo":"MA"},{"colors":"#999292","id":685985876,"geo":"MA"},{"colors":"#2d324f","id":685138675,"geo":"MA"},{"colors":"#323536","id":690971915,"geo":"MA"},{"colors":"#486554","id":802325246,"geo":"MA"},{"colors":"#777b76","id":691446542,"geo":"MA"},{"colors":"#7d7561","id":693046795,"geo":"MA"},{"colors":"#6d6751","id":666540752,"geo":"MA"},{"colors":"#b18d84","id":696300325,"geo":"MA"},{"colors":"#41505f","id":694693235,"geo":"MA"},{"colors":"#51676e","id":693042552,"geo":"MA"},{"colors":"#7b8a7e","id":694693232,"geo":"MA"},{"colors":"#8a939c","id":692350546,"geo":"MA"},{"colors":"#b6b6aa","id":697025361,"geo":"MA"},{"colors":"#303053","id":695623010,"geo":"MA"},{"colors":"#a2a896","id":697548704,"geo":"MA"},{"colors":"#5a6c70","id":697404583,"geo":"MA"},{"colors":"#606374","id":700517674,"geo":"MA"},{"colors":"#7c8383","id":696263465,"geo":"MA"},{"colors":"#696a5f","id":697853657,"geo":"MA"},{"colors":"#a09e97","id":697676300,"geo":"MA"},{"colors":"#303747","id":698351406,"geo":"MA"},{"colors":"#3e4458","id":703241776,"geo":"MA"},{"colors":"#b7b29f","id":701735270,"geo":"MA"},{"colors":"#535054","id":700898556,"geo":"MA"},{"colors":"#6287a4","id":704182332,"geo":"MA"},{"colors":"#556779","id":699579428,"geo":"MA"},{"colors":"#838068","id":704734968,"geo":"MA"},{"colors":"#75706a","id":692350536,"geo":"MA"},{"colors":"#8b8794","id":706782788,"geo":"MA"},{"colors":"#928c81","id":706686256,"geo":"MA"},{"colors":"#586e5d","id":705739566,"geo":"MA"},{"colors":"#9c93a2","id":706782786,"geo":"MA"},{"colors":"#656866","id":707006827,"geo":"MA"},{"colors":"#797981","id":708980380,"geo":"MA"},{"colors":"#778572","id":709017025,"geo":"MA"},{"colors":"#5c585a","id":704030833,"geo":"MA"},{"colors":"#c3c9ca","id":704855142,"geo":"MA"},{"colors":"#a19795","id":707530706,"geo":"MA"},{"colors":"#a69d8f","id":709017024,"geo":"MA"},{"colors":"#88867a","id":712902839,"geo":"MA"},{"colors":"#737060","id":708027409,"geo":"MA"},{"colors":"#99a098","id":713150713,"geo":"MA"},{"colors":"#b5b6af","id":713150708,"geo":"MA"},{"colors":"#bbc5c9","id":709788734,"geo":"MA"},{"colors":"#526f95","id":709788783,"geo":"MA"},{"colors":"#595d42","id":710575680,"geo":"MA"},{"colors":"#918b84","id":715220723,"geo":"MA"},{"colors":"#c1bdb6","id":712124287,"geo":"MA"},{"colors":"#909485","id":718496201,"geo":"MA"},{"colors":"#7d8282","id":718446514,"geo":"MA"},{"colors":"#8d8586","id":718491710,"geo":"MA"},{"colors":"#5f605e","id":720252421,"geo":"MA"},{"colors":"#9ba6aa","id":720302618,"geo":"MA"},{"colors":"#b7b5ad","id":722012307,"geo":"MA"},{"colors":"#6e6f84","id":713152639,"geo":"MA"},{"colors":"#c9b3a2","id":722644004,"geo":"MA"},{"colors":"#828c7a","id":719409999,"geo":"MA"},{"colors":"#323e45","id":718494334,"geo":"MA"},{"colors":"#a6a698","id":722643456,"geo":"MA"},{"colors":"#767f74","id":722645143,"geo":"MA"},{"colors":"#7f9088","id":711363845,"geo":"MA"},{"colors":"#95a29c","id":722644186,"geo":"MA"},{"colors":"#6c9094","id":722642990,"geo":"MA"},{"colors":"#989f8e","id":724448447,"geo":"MA"},{"colors":"#9eaab1","id":723630244,"geo":"MA"},{"colors":"#525561","id":720739672,"geo":"MA"},{"colors":"#989383","id":722645707,"geo":"MA"},{"colors":"#aaaaac","id":722068400,"geo":"MA"},{"colors":"#707e8f","id":726569645,"geo":"MA"},{"colors":"#9ca591","id":725457017,"geo":"MA"},{"colors":"#6e92a8","id":725388378,"geo":"MA"},{"colors":"#323039","id":876395728,"geo":"MA"},{"colors":"#adafab","id":729211060,"geo":"MA"},{"colors":"#878483","id":727305587,"geo":"MA"},{"colors":"#899785","id":724154203,"geo":"MA"},{"colors":"#ababaa","id":729211065,"geo":"MA"},{"colors":"#a69b8a","id":729222664,"geo":"MA"},{"colors":"#8c8280","id":729220370,"geo":"MA"},{"colors":"#283538","id":714020158,"geo":"MA"},{"colors":"#a39f98","id":734543307,"geo":"MA"},{"colors":"#a49895","id":737115604,"geo":"MA"},{"colors":"#94908b","id":743773002,"geo":"MA"},{"colors":"#455656","id":747310891,"geo":"MA"},{"colors":"#34504c","id":740852742,"geo":"MA"},{"colors":"#364538","id":730030642,"geo":"MA"},{"colors":"#4f77a6","id":750980794,"geo":"MA"},{"colors":"#6b9896","id":748818605,"geo":"MA"},{"colors":"#9ba7a0","id":729367229,"geo":"MA"},{"colors":"#8b9c8d","id":745449901,"geo":"MA"},{"colors":"#8e9297","id":724643789,"geo":"MA"},{"colors":"#626778","id":751956222,"geo":"MA"},{"colors":"#847b74","id":737378538,"geo":"MA"},{"colors":"#776f83","id":754090471,"geo":"MA"},{"colors":"#4b443f","id":752838367,"geo":"MA"},{"colors":"#3a5246","id":750318440,"geo":"MA"},{"colors":"#4e4e52","id":754105266,"geo":"MA"},{"colors":"#869b83","id":758404994,"geo":"MA"},{"colors":"#494a59","id":754381371,"geo":"MA"},{"colors":"#9e9e92","id":742981372,"geo":"MA"},{"colors":"#81ac8b","id":756795150,"geo":"MA"},{"colors":"#3d4d57","id":737542253,"geo":"MA"},{"colors":"#595e53","id":757301961,"geo":"MA"},{"colors":"#597d90","id":754095176,"geo":"MA"},{"colors":"#8d9d78","id":760871456,"geo":"MA"},{"colors":"#b7ab9d","id":760070957,"geo":"MA"},{"colors":"#7a809a","id":761861510,"geo":"MA"},{"colors":"#797e79","id":761345877,"geo":"MA"},{"colors":"#8d696a","id":760195146,"geo":"MA"},{"colors":"#3f4b45","id":763196233,"geo":"MA"},{"colors":"#b6b4b0","id":783205162,"geo":"MA"},{"colors":"#939c92","id":772045476,"geo":"MA"},{"colors":"#70919e","id":771747979,"geo":"MA"},{"colors":"#bdbdb5","id":757291974,"geo":"MA"},{"colors":"#979c8a","id":782813694,"geo":"MA"},{"colors":"#434748","id":788028316,"geo":"MA"},{"colors":"#aeaaa5","id":790465120,"geo":"MA"},{"colors":"#9a9496","id":777306509,"geo":"MA"},{"colors":"#b6b3ad","id":787006106,"geo":"MA"},{"colors":"#b3afaa","id":762312626,"geo":"MA"},{"colors":"#41575c","id":788311712,"geo":"MA"},{"colors":"#5c655b","id":793455031,"geo":"MA"},{"colors":"#a4767d","id":796598925,"geo":"MA"},{"colors":"#a28e7c","id":790465119,"geo":"MA"},{"colors":"#81748a","id":793590353,"geo":"MA"},{"colors":"#6e696e","id":798462386,"geo":"MA"},{"colors":"#0d1124","id":797673264,"geo":"MA"},{"colors":"#434254","id":790455098,"geo":"MA"},{"colors":"#4d5e79","id":798546136,"geo":"MA"},{"colors":"#a29f9f","id":807335751,"geo":"MA"},{"colors":"#5a605c","id":804697586,"geo":"MA"},{"colors":"#525866","id":798463633,"geo":"MA"},{"colors":"#a0aba5","id":807611463,"geo":"MA"},{"colors":"#5f8b9e","id":806490990,"geo":"MA"},{"colors":"#3c454c","id":798464004,"geo":"MA"},{"colors":"#272a36","id":798462384,"geo":"MA"},{"colors":"#7c787b","id":798462387,"geo":"MA"},{"colors":"#9a8576","id":810155060,"geo":"MA"},{"colors":"#484b42","id":806930670,"geo":"MA"},{"colors":"#a49e93","id":813981996,"geo":"MA"},{"colors":"#645e5d","id":808544430,"geo":"MA"},{"colors":"#668ba5","id":814773789,"geo":"MA"},{"colors":"#455352","id":814784756,"geo":"MA"},{"colors":"#b96d71","id":814723917,"geo":"MA"},{"colors":"#8f838a","id":814723969,"geo":"MA"},{"colors":"#aba693","id":817259128,"geo":"MA"},{"colors":"#a59b96","id":816626877,"geo":"MA"},{"colors":"#908f91","id":815675331,"geo":"MA"},{"colors":"#57615b","id":813954221,"geo":"MA"},{"colors":"#676d7d","id":821942025,"geo":"MA"},{"colors":"#80a57a","id":815548809,"geo":"MA"},{"colors":"#63577d","id":823675442,"geo":"MA"},{"colors":"#636e4f","id":814689599,"geo":"MA"},{"colors":"#737784","id":818263436,"geo":"MA"},{"colors":"#a0abac","id":817362842,"geo":"MA"},{"colors":"#58565d","id":815675318,"geo":"MA"},{"colors":"#a1938f","id":818624655,"geo":"MA"},{"colors":"#3e4449","id":823024169,"geo":"MA"},{"colors":"#9b9097","id":823680540,"geo":"MA"},{"colors":"#475349","id":822356063,"geo":"MA"},{"colors":"#6eb4a9","id":830411685,"geo":"MA"},{"colors":"#aca8a4","id":823987884,"geo":"MA"},{"colors":"#a6aa87","id":828600314,"geo":"MA"},{"colors":"#bfbbb5","id":829925859,"geo":"MA"},{"colors":"#696f6d","id":832669954,"geo":"MA"},{"colors":"#55474b","id":825415168,"geo":"MA"},{"colors":"#9a9d9b","id":827658478,"geo":"MA"},{"colors":"#6c7065","id":830826503,"geo":"MA"},{"colors":"#87a5b9","id":833311986,"geo":"MA"},{"colors":"#74939e","id":837715136,"geo":"MA"},{"colors":"#596a88","id":841385702,"geo":"MA"},{"colors":"#8e916d","id":830740990,"geo":"MA"},{"colors":"#4a4d4a","id":848753620,"geo":"MA"},{"colors":"#7a7a50","id":837585137,"geo":"MA"},{"colors":"#86875a","id":828333565,"geo":"MA"},{"colors":"#bfc1b1","id":834250253,"geo":"MA"},{"colors":"#4f5469","id":855661450,"geo":"MA"},{"colors":"#676961","id":856193829,"geo":"MA"},{"colors":"#8d9c97","id":846320281,"geo":"MA"},{"colors":"#c0bdb6","id":847331414,"geo":"MA"},{"colors":"#696a5c","id":856193821,"geo":"MA"},{"colors":"#929780","id":856077390,"geo":"MA"},{"colors":"#4f495a","id":855211851,"geo":"MA"},{"colors":"#67675f","id":856193833,"geo":"MA"},{"colors":"#928675","id":838368476,"geo":"MA"},{"colors":"#83a097","id":868931220,"geo":"MA"},{"colors":"#c0b3ae","id":868809274,"geo":"MA"},{"colors":"#dddacd","id":857589656,"geo":"MA"},{"colors":"#425148","id":499542765,"geo":"MA"},{"colors":"#565f55","id":436606087,"geo":"MA"},{"colors":"#394845","id":480257080,"geo":"MA"},{"colors":"#6c7464","id":615639232,"geo":"MA"},{"colors":"#5a6454","id":556140477,"geo":"MA"},{"colors":"#2a2c27","id":481289503,"geo":"MA"},{"colors":"#434c3d","id":615639229,"geo":"MA"},{"colors":"#1a1d1b","id":659767957,"geo":"MA"},{"colors":"#3e4842","id":608106794,"geo":"MA"},{"colors":"#24241e","id":727431091,"geo":"MA"},{"colors":"#456240","id":695294230,"geo":"MA"},{"colors":"#232220","id":697035448,"geo":"MA"},{"colors":"#75716e","id":796684261,"geo":"MA"},{"colors":"#3a4733","id":846778795,"geo":"MA"},{"colors":"#586053","id":796684262,"geo":"MA"},{"colors":"#6e7061","id":823023464,"geo":"MA"},{"colors":"#303338","id":826206505,"geo":"MA"},{"colors":"#6e7b5c","id":852226551,"geo":"MA"},{"colors":"#4e5348","id":697236175,"geo":"MA"},{"colors":"#77846e","id":695294228,"geo":"MA"},{"colors":"#4f514f","id":783782133,"geo":"MA"},{"colors":"#4e5d49","id":697633552,"geo":"MA"},{"colors":"#5e5c6e","id":879052652,"geo":"MA"},{"colors":"#849195","id":894843597,"geo":"MA"},{"colors":"#4a5476","id":888777222,"geo":"MA"},{"colors":"#3a4249","id":901601312,"geo":"MA"},{"colors":"#6c686b","id":886011717,"geo":"MA"},{"colors":"#5a5e63","id":902150481,"geo":"MA"},{"colors":"#696d72","id":901598967,"geo":"MA"},{"colors":"#857d7e","id":901685346,"geo":"MA"},{"colors":"#6d6c83","id":903913392,"geo":"MA"},{"colors":"#434a6a","id":901594317,"geo":"MA"},{"colors":"#3b476a","id":909825229,"geo":"MA"},{"colors":"#899096","id":914140176,"geo":"MA"},{"colors":"#6f7175","id":913594963,"geo":"MA"},{"colors":"#828169","id":910589677,"geo":"MA"},{"colors":"#828ba0","id":918089473,"geo":"MA"},{"colors":"#2e3540","id":914692196,"geo":"MA"},{"colors":"#7c7373","id":938565244,"geo":"MA"},{"colors":"#5b4d57","id":920613964,"geo":"MA"},{"colors":"#807c86","id":969638276,"geo":"MA"},{"colors":"#6b6455","id":885343672,"geo":"MA"},{"colors":"#858da7","id":971263341,"geo":"MA"},{"colors":"#7e7e83","id":937358915,"geo":"MA"},{"colors":"#334733","id":981828865,"geo":"MA"},{"colors":"#9e8b81","id":935240556,"geo":"MA"},{"colors":"#68676e","id":974105301,"geo":"MA"},{"colors":"#887a7e","id":987503791,"geo":"MA"},{"colors":"#3f403f","id":990217046,"geo":"MA"},{"colors":"#3e445c","id":999063445,"geo":"MA"},{"colors":"#707759","id":1000644818,"geo":"MA"},{"colors":"#847e76","id":1001864120,"geo":"MA"},{"colors":"#8d8890","id":1005640217,"geo":"MA"},{"colors":"#45526b","id":990217128,"geo":"MA"},{"colors":"#8e8d8c","id":1007508803,"geo":"MA"},{"colors":"#373147","id":997805961,"geo":"MA"},{"colors":"#8499da","id":1008958437,"geo":"MA"},{"colors":"#505f45","id":1009717717,"geo":"MA"},{"colors":"#9e9898","id":1012314806,"geo":"MA"},{"colors":"#b6977b","id":1014533766,"geo":"MA"},{"colors":"#a6a8af","id":1001864128,"geo":"MA"},{"colors":"#70788b","id":1016394918,"geo":"MA"},{"colors":"#4d4a49","id":1028708049,"geo":"MA"},{"colors":"#bfcee9","id":1007508780,"geo":"MA"},{"colors":"#4f524d","id":1016450309,"geo":"MA"},{"colors":"#101e37","id":1023650752,"geo":"MA"},{"colors":"#656147","id":1033953438,"geo":"MA"},{"colors":"#3c3f2f","id":1032760629,"geo":"MA"},{"colors":"#4b5945","id":1032742301,"geo":"MA"},{"colors":"#676c73","id":987424691,"geo":"MA"},{"colors":"#8f6c6d","id":1016693341,"geo":"MA"},{"colors":"#7f787b","id":1033380215,"geo":"MA"},{"colors":"#627345","id":1034231905,"geo":"MA"},{"colors":"#8e907e","id":960846428,"geo":"MA"},{"colors":"#85857f","id":950005794,"geo":"MA"},{"colors":"#7b7573","id":1034901888,"geo":"MA"},{"colors":"#757777","id":1035258876,"geo":"MA"},{"colors":"#625d63","id":1043830638,"geo":"MA"},{"colors":"#b9ae91","id":1041738381,"geo":"MA"},{"colors":"#292f30","id":1038108619,"geo":"MA"},{"colors":"#8b8b8e","id":1046310458,"geo":"MA"},{"colors":"#556744","id":1046874211,"geo":"MA"},{"colors":"#a69c8e","id":1049677011,"geo":"MA"},{"colors":"#6d6a5b","id":1053099024,"geo":"MA"},{"colors":"#212130","id":1051330082,"geo":"MA"},{"colors":"#3a4731","id":1039718418,"geo":"MA"},{"colors":"#7b7568","id":1054592515,"geo":"MA"},{"colors":"#656464","id":1057874152,"geo":"MA"},{"colors":"#8b9881","id":1064897393,"geo":"MA"},{"colors":"#4b4b46","id":1073462541,"geo":"MA"},{"colors":"#757c63","id":1066611832,"geo":"MA"},{"colors":"#6c6868","id":1080490266,"geo":"MA"},{"colors":"#62615b","id":1080265057,"geo":"MA"},{"colors":"#404974","id":1087102822,"geo":"MA"},{"colors":"#6c707c","id":1063630111,"geo":"MA"},{"colors":"#635e5c","id":1062419206,"geo":"MA"},{"colors":"#6c6872","id":1084263684,"geo":"MA"},{"colors":"#837d76","id":1053099022,"geo":"MA"},{"colors":"#797d87","id":1088018499,"geo":"MA"},{"colors":"#6f6e65","id":1087784472,"geo":"MA"},{"colors":"#646969","id":1087768821,"geo":"MA"},{"colors":"#9e9b9b","id":1089053168,"geo":"MA"},{"colors":"#5e6178","id":1089574034,"geo":"MA"},{"colors":"#3e4672","id":1089867677,"geo":"MA"},{"colors":"#6e6a64","id":1086683364,"geo":"MA"},{"colors":"#615a56","id":1089712750,"geo":"MA"},{"colors":"#89867a","id":1089958527,"geo":"MA"},{"colors":"#4c5c85","id":1089724337,"geo":"MA"},{"colors":"#767583","id":1090330539,"geo":"MA"},{"colors":"#778283","id":1090330541,"geo":"MA"},{"colors":"#6a6e81","id":1090804220,"geo":"MA"},{"colors":"#4b434f","id":1090771526,"geo":"MA"},{"colors":"#414c6c","id":1091269517,"geo":"MA"},{"colors":"#ad9e93","id":1095726382,"geo":"MA"},{"colors":"#534f55","id":1090771525,"geo":"MA"},{"colors":"#79777d","id":1095733078,"geo":"MA"},{"colors":"#636869","id":1095950854,"geo":"MA"},{"colors":"#e97b5a","id":1094928360,"geo":"MA"},{"colors":"#4e5c68","id":1095950826,"geo":"MA"},{"colors":"#435252","id":1095633598,"geo":"MA"},{"colors":"#8c8481","id":1095494696,"geo":"MA"},{"colors":"#86848a","id":1096970064,"geo":"MA"},{"colors":"#88878a","id":1096970043,"geo":"MA"},{"colors":"#969591","id":1097335385,"geo":"MA"},{"colors":"#6e6e77","id":1096970052,"geo":"MA"},{"colors":"#b5a182","id":1098798869,"geo":"MA"},{"colors":"#544445","id":1098798889,"geo":"MA"},{"colors":"#727478","id":1096714267,"geo":"MA"},{"colors":"#7e7b6d","id":1098798875,"geo":"MA"},{"colors":"#57535d","id":1099429762,"geo":"MA"},{"colors":"#9c7b7e","id":1103884072,"geo":"MA"},{"colors":"#5c5a55","id":1106822303,"geo":"MA"},{"colors":"#656f61","id":1099745421,"geo":"MA"},{"colors":"#88807b","id":1110049353,"geo":"MA"},{"colors":"#4f5768","id":1107085141,"geo":"MA"},{"colors":"#7e7c80","id":1110918369,"geo":"MA"},{"colors":"#989393","id":1114776406,"geo":"MA"},{"colors":"#9a9ca3","id":1107080275,"geo":"MA"},{"colors":"#676a6f","id":1105225142,"geo":"MA"},{"colors":"#a6a29e","id":1113201313,"geo":"MA"},{"colors":"#4f5d4b","id":1125752818,"geo":"MA"},{"colors":"#70725e","id":1125752891,"geo":"MA"},{"colors":"#858999","id":1125752881,"geo":"MA"},{"colors":"#7d787a","id":1130108741,"geo":"MA"},{"colors":"#344245","id":1134182820,"geo":"MA"},{"colors":"#5a6172","id":1134298948,"geo":"MA"},{"colors":"#263034","id":1136976879,"geo":"MA"},{"colors":"#7d806b","id":1125752809,"geo":"MA"},{"colors":"#25273e","id":1137966984,"geo":"MA"},{"colors":"#9f9992","id":1144237091,"geo":"MA"},{"colors":"#4a5065","id":1144237094,"geo":"MA"},{"colors":"#91969b","id":1147038205,"geo":"MA"},{"colors":"#576365","id":1157309466,"geo":"MA"},{"colors":"#666d6a","id":1160272103,"geo":"MA"},{"colors":"#3c4254","id":1158826395,"geo":"MA"},{"colors":"#727574","id":1158477234,"geo":"MA"},{"colors":"#505b5a","id":1164896875,"geo":"MA"},{"colors":"#797f7c","id":1161473068,"geo":"MA"},{"colors":"#494b4f","id":1172236179,"geo":"MA"},{"colors":"#754e47","id":1148348634,"geo":"MA"},{"colors":"#404d73","id":1172893877,"geo":"MA"},{"colors":"#656873","id":1168154198,"geo":"MA"},{"colors":"#6c8b8b","id":880006522,"geo":"MA"},{"colors":"#828786","id":878040526,"geo":"MA"},{"colors":"#686444","id":1198806392,"geo":"MA"},{"colors":"#73814c","id":877975392,"geo":"MA"},{"colors":"#5f686b","id":886533524,"geo":"MA"},{"colors":"#6b737b","id":886599016,"geo":"MA"},{"colors":"#474853","id":1122756865,"geo":"MA"},{"colors":"#5e5f69","id":1121894471,"geo":"MA"},{"colors":"#706e6d","id":1122418192,"geo":"MA"},{"colors":"#3f3c3e","id":1198163621,"geo":"MA"},{"colors":"#323436","id":1197825702,"geo":"MA"},{"colors":"#c0b9ac","id":889593888,"geo":"MA"},{"colors":"#706154","id":894324220,"geo":"MA"},{"colors":"#4c5c43","id":891493640,"geo":"MA"},{"colors":"#9ab3a5","id":897358459,"geo":"MA"},{"colors":"#829287","id":893811656,"geo":"MA"},{"colors":"#61746b","id":894433482,"geo":"MA"},{"colors":"#b1abb3","id":894057676,"geo":"MA"},{"colors":"#596c54","id":895877496,"geo":"MA"},{"colors":"#92958d","id":897540631,"geo":"MA"},{"colors":"#4d5970","id":899711708,"geo":"MA"},{"colors":"#6a5558","id":889407784,"geo":"MA"},{"colors":"#504d56","id":901714322,"geo":"MA"},{"colors":"#71917a","id":899569471,"geo":"MA"},{"colors":"#9c948e","id":903732540,"geo":"MA"},{"colors":"#758c84","id":900232170,"geo":"MA"},{"colors":"#959188","id":903412895,"geo":"MA"},{"colors":"#56554c","id":904635957,"geo":"MA"},{"colors":"#95a0aa","id":904633631,"geo":"MA"},{"colors":"#7a7473","id":905685693,"geo":"MA"},{"colors":"#46423b","id":901685330,"geo":"MA"},{"colors":"#a09580","id":905176633,"geo":"MA"},{"colors":"#8b8a85","id":906212590,"geo":"MA"},{"colors":"#999695","id":907849994,"geo":"MA"},{"colors":"#63655d","id":905846595,"geo":"MA"},{"colors":"#b49b85","id":900968897,"geo":"MA"},{"colors":"#82b58d","id":902143253,"geo":"MA"},{"colors":"#5d5a51","id":908098476,"geo":"MA"},{"colors":"#b5c2c5","id":906965915,"geo":"MA"},{"colors":"#717a6d","id":909632936,"geo":"MA"},{"colors":"#505a3e","id":907196299,"geo":"MA"},{"colors":"#252b42","id":909352795,"geo":"MA"},{"colors":"#d5c8b1","id":910577376,"geo":"MA"},{"colors":"#a8a89e","id":910579934,"geo":"MA"},{"colors":"#6d7278","id":912491872,"geo":"MA"},{"colors":"#6f6f70","id":912866323,"geo":"MA"},{"colors":"#5c554a","id":910132472,"geo":"MA"},{"colors":"#6a6d6b","id":909828263,"geo":"MA"},{"colors":"#a2a199","id":917193368,"geo":"MA"},{"colors":"#aba7a3","id":917297350,"geo":"MA"},{"colors":"#8d8f97","id":918073013,"geo":"MA"},{"colors":"#80969f","id":906329054,"geo":"MA"},{"colors":"#4c4467","id":911280891,"geo":"MA"},{"colors":"#566a97","id":918746206,"geo":"MA"},{"colors":"#968f88","id":909128926,"geo":"MA"},{"colors":"#aaabad","id":919250241,"geo":"MA"},{"colors":"#626362","id":919860640,"geo":"MA"},{"colors":"#94a0ad","id":919250256,"geo":"MA"},{"colors":"#7f7a49","id":920861220,"geo":"MA"},{"colors":"#2b3c51","id":920900841,"geo":"MA"},{"colors":"#ada393","id":921779261,"geo":"MA"},{"colors":"#394254","id":920877726,"geo":"MA"},{"colors":"#67606a","id":927274631,"geo":"MA"},{"colors":"#837f7b","id":922690687,"geo":"MA"},{"colors":"#927579","id":919250237,"geo":"MA"},{"colors":"#34322c","id":922478873,"geo":"MA"},{"colors":"#aea594","id":921819196,"geo":"MA"},{"colors":"#a8b3c2","id":922468759,"geo":"MA"},{"colors":"#5c6880","id":922768951,"geo":"MA"},{"colors":"#516765","id":918319375,"geo":"MA"},{"colors":"#7fbbbd","id":934763985,"geo":"MA"},{"colors":"#70867d","id":939566014,"geo":"MA"},{"colors":"#55596b","id":938620925,"geo":"MA"},{"colors":"#95928e","id":947596229,"geo":"MA"},{"colors":"#242c37","id":944736023,"geo":"MA"},{"colors":"#948c92","id":931566241,"geo":"MA"},{"colors":"#a3909f","id":947840844,"geo":"MA"},{"colors":"#3c4b48","id":958039088,"geo":"MA"},{"colors":"#83af8b","id":939842471,"geo":"MA"},{"colors":"#928f86","id":920861251,"geo":"MA"},{"colors":"#525550","id":966624512,"geo":"MA"},{"colors":"#5b6b65","id":966671397,"geo":"MA"},{"colors":"#52524d","id":969791843,"geo":"MA"},{"colors":"#97978b","id":933629737,"geo":"MA"},{"colors":"#222d42","id":971030640,"geo":"MA"},{"colors":"#ccc2b1","id":972954982,"geo":"MA"},{"colors":"#385780","id":972611670,"geo":"MA"},{"colors":"#9a928b","id":924352369,"geo":"MA"},{"colors":"#69717f","id":973577045,"geo":"MA"},{"colors":"#b9acb5","id":974105669,"geo":"MA"},{"colors":"#6e7070","id":975354907,"geo":"MA"},{"colors":"#536ea5","id":974105612,"geo":"MA"},{"colors":"#68626b","id":970990926,"geo":"MA"},{"colors":"#242b3d","id":988191224,"geo":"MA"},{"colors":"#44495e","id":991822508,"geo":"MA"},{"colors":"#8f8c81","id":992766608,"geo":"MA"},{"colors":"#839f96","id":960946981,"geo":"MA"},{"colors":"#605968","id":984473262,"geo":"MA"},{"colors":"#90aac1","id":1000340822,"geo":"MA"},{"colors":"#cbc1b4","id":997714255,"geo":"MA"},{"colors":"#adb1a2","id":999606826,"geo":"MA"},{"colors":"#aba495","id":997190049,"geo":"MA"},{"colors":"#ac9b9b","id":1000679300,"geo":"MA"},{"colors":"#999685","id":1001141698,"geo":"MA"},{"colors":"#53644b","id":988775223,"geo":"MA"},{"colors":"#726c66","id":981844747,"geo":"MA"},{"colors":"#39426d","id":1016693338,"geo":"MA"},{"colors":"#70add0","id":1001845821,"geo":"MA"},{"colors":"#737165","id":1019359135,"geo":"MA"},{"colors":"#738daf","id":1020896956,"geo":"MA"},{"colors":"#8cbcaa","id":1020896917,"geo":"MA"},{"colors":"#696968","id":1020897003,"geo":"MA"},{"colors":"#8d8b91","id":1020896986,"geo":"MA"},{"colors":"#b87c7c","id":1028155604,"geo":"MA"},{"colors":"#919ca0","id":1021988269,"geo":"MA"},{"colors":"#73727d","id":1029909726,"geo":"MA"},{"colors":"#948a81","id":1002427233,"geo":"MA"},{"colors":"#75b3d7","id":1021673541,"geo":"MA"},{"colors":"#92a28f","id":1015439626,"geo":"MA"},{"colors":"#475a62","id":1038904879,"geo":"MA"},{"colors":"#4f5a61","id":1030086257,"geo":"MA"},{"colors":"#2d3b50","id":1021941501,"geo":"MA"},{"colors":"#736268","id":1030405544,"geo":"MA"},{"colors":"#515949","id":1039231455,"geo":"MA"},{"colors":"#6d707a","id":1040399705,"geo":"MA"},{"colors":"#b8c3d2","id":1040045998,"geo":"MA"},{"colors":"#6e706a","id":1039748130,"geo":"MA"},{"colors":"#b0b2a4","id":1038904877,"geo":"MA"},{"colors":"#6e6c66","id":1040628995,"geo":"MA"},{"colors":"#756c74","id":1044301555,"geo":"MA"},{"colors":"#89896f","id":1042432369,"geo":"MA"},{"colors":"#938d8e","id":1043623454,"geo":"MA"},{"colors":"#979996","id":1049707026,"geo":"MA"},{"colors":"#a69e9b","id":1049396557,"geo":"MA"},{"colors":"#7e8078","id":1050650364,"geo":"MA"},{"colors":"#607288","id":1051141342,"geo":"MA"},{"colors":"#6697a4","id":1049706996,"geo":"MA"},{"colors":"#7b5350","id":1051432104,"geo":"MA"},{"colors":"#a49e96","id":1051432059,"geo":"MA"},{"colors":"#afb3ac","id":1052849383,"geo":"MA"},{"colors":"#93b192","id":1051440216,"geo":"MA"},{"colors":"#626071","id":1051161216,"geo":"MA"},{"colors":"#a19b8f","id":1049492893,"geo":"MA"},{"colors":"#88878b","id":1052852097,"geo":"MA"},{"colors":"#5f83a9","id":1053808390,"geo":"MA"},{"colors":"#81a096","id":1054531411,"geo":"MA"},{"colors":"#5d5d52","id":1055982089,"geo":"MA"},{"colors":"#abaca2","id":1058347821,"geo":"MA"},{"colors":"#5f6c61","id":1060166650,"geo":"MA"},{"colors":"#a9a59f","id":1059411913,"geo":"MA"},{"colors":"#989988","id":1060114098,"geo":"MA"},{"colors":"#907e72","id":1063134401,"geo":"MA"},{"colors":"#6d6a69","id":1063134412,"geo":"MA"},{"colors":"#8d8a90","id":1063134424,"geo":"MA"},{"colors":"#868066","id":1063134311,"geo":"MA"},{"colors":"#adadab","id":1066213747,"geo":"MA"},{"colors":"#707565","id":1066213815,"geo":"MA"},{"colors":"#91a27e","id":1066551915,"geo":"MA"},{"colors":"#666f61","id":1060912796,"geo":"MA"},{"colors":"#5b8cac","id":1072158725,"geo":"MA"},{"colors":"#7d7f6c","id":1068664854,"geo":"MA"},{"colors":"#859fb0","id":1070109522,"geo":"MA"},{"colors":"#ca9672","id":1072158731,"geo":"MA"},{"colors":"#aaa69f","id":1075443607,"geo":"MA"},{"colors":"#a8b5af","id":1074074771,"geo":"MA"},{"colors":"#cecec5","id":1064981293,"geo":"MA"},{"colors":"#9d9b9e","id":1070109534,"geo":"MA"},{"colors":"#b4b4b7","id":1075443572,"geo":"MA"},{"colors":"#727477","id":1079257894,"geo":"MA"},{"colors":"#6b6864","id":1079341052,"geo":"MA"},{"colors":"#6b7152","id":1073695672,"geo":"MA"},{"colors":"#6f8089","id":1077490140,"geo":"MA"},{"colors":"#a38e99","id":1078835996,"geo":"MA"},{"colors":"#464c4e","id":1080054439,"geo":"MA"},{"colors":"#96a698","id":1082212244,"geo":"MA"},{"colors":"#4b5e85","id":1082576633,"geo":"MA"},{"colors":"#81a785","id":1082211261,"geo":"MA"},{"colors":"#5f6e90","id":1082576641,"geo":"MA"},{"colors":"#898485","id":1083610018,"geo":"MA"},{"colors":"#b2b3b5","id":1084319322,"geo":"MA"},{"colors":"#88a27a","id":1086418036,"geo":"MA"},{"colors":"#5a6f83","id":1079257861,"geo":"MA"},{"colors":"#4b4849","id":1082790851,"geo":"MA"},{"colors":"#99a37c","id":1084102684,"geo":"MA"},{"colors":"#e4c2a0","id":1088031745,"geo":"MA"},{"colors":"#7babc8","id":1088031731,"geo":"MA"},{"colors":"#63686e","id":1087793065,"geo":"MA"},{"colors":"#87b6d2","id":1088031743,"geo":"MA"},{"colors":"#b3aea6","id":1088450425,"geo":"MA"},{"colors":"#636877","id":1088179882,"geo":"MA"},{"colors":"#979695","id":1088450448,"geo":"MA"},{"colors":"#bbbab4","id":1088939879,"geo":"MA"},{"colors":"#96c59d","id":1088450453,"geo":"MA"},{"colors":"#cd9675","id":1089847865,"geo":"MA"},{"colors":"#b7b6b5","id":1090299716,"geo":"MA"},{"colors":"#7f7f83","id":1088939853,"geo":"MA"},{"colors":"#2854b0","id":1090244442,"geo":"MA"},{"colors":"#bab2ab","id":1092188537,"geo":"MA"},{"colors":"#40465b","id":1089724329,"geo":"MA"},{"colors":"#515747","id":1093475701,"geo":"MA"},{"colors":"#8e9ba1","id":1093475698,"geo":"MA"},{"colors":"#6ea591","id":1093700123,"geo":"MA"},{"colors":"#659091","id":1093947516,"geo":"MA"},{"colors":"#877993","id":1093700121,"geo":"MA"},{"colors":"#6c685f","id":1095494690,"geo":"MA"},{"colors":"#777d62","id":1090299719,"geo":"MA"},{"colors":"#98a794","id":1097137021,"geo":"MA"},{"colors":"#c1aa9f","id":1097142485,"geo":"MA"},{"colors":"#aa9c8e","id":1097142513,"geo":"MA"},{"colors":"#69708d","id":1095726467,"geo":"MA"},{"colors":"#7b7673","id":1097142529,"geo":"MA"},{"colors":"#7c787c","id":1097142538,"geo":"MA"},{"colors":"#565157","id":1093469399,"geo":"MA"},{"colors":"#aca49d","id":1097142470,"geo":"MA"},{"colors":"#c4c4b8","id":1097137033,"geo":"MA"},{"colors":"#90938e","id":1097263945,"geo":"MA"},{"colors":"#beb7ae","id":1097340481,"geo":"MA"},{"colors":"#7a7e84","id":1097263951,"geo":"MA"},{"colors":"#767865","id":1097780355,"geo":"MA"},{"colors":"#b3aca7","id":1098676694,"geo":"MA"},{"colors":"#697d8a","id":1098798896,"geo":"MA"},{"colors":"#706f6b","id":1097989679,"geo":"MA"},{"colors":"#42668e","id":1100735564,"geo":"MA"},{"colors":"#5a6775","id":1103254386,"geo":"MA"},{"colors":"#95b8d5","id":1104521417,"geo":"MA"},{"colors":"#6d6365","id":1103688830,"geo":"MA"},{"colors":"#cd8e94","id":1097142461,"geo":"MA"},{"colors":"#36444c","id":1113201394,"geo":"MA"},{"colors":"#81887b","id":1104198841,"geo":"MA"},{"colors":"#686d78","id":1104521419,"geo":"MA"},{"colors":"#687369","id":1104661353,"geo":"MA"},{"colors":"#60725f","id":1104661361,"geo":"MA"},{"colors":"#88a1c0","id":1104930894,"geo":"MA"},{"colors":"#5a5a4e","id":1105803364,"geo":"MA"},{"colors":"#3c3c3b","id":1104661372,"geo":"MA"},{"colors":"#89a0a1","id":1107392879,"geo":"MA"},{"colors":"#91645d","id":1106454658,"geo":"MA"},{"colors":"#929292","id":1099468443,"geo":"MA"},{"colors":"#646763","id":1106454640,"geo":"MA"},{"colors":"#647a95","id":1106474109,"geo":"MA"},{"colors":"#aea69a","id":1106454626,"geo":"MA"},{"colors":"#60656e","id":1107747879,"geo":"MA"},{"colors":"#9ea2a6","id":1112266926,"geo":"MA"},{"colors":"#ababa8","id":1112025827,"geo":"MA"},{"colors":"#717479","id":1110271916,"geo":"MA"},{"colors":"#6d756b","id":1112408555,"geo":"MA"},{"colors":"#b3c4c8","id":1115073879,"geo":"MA"},{"colors":"#555b4d","id":1113343728,"geo":"MA"},{"colors":"#6d666c","id":1115776656,"geo":"MA"},{"colors":"#534e5b","id":1103270143,"geo":"MA"},{"colors":"#889d93","id":1113151164,"geo":"MA"},{"colors":"#5f6d8b","id":1117244747,"geo":"MA"},{"colors":"#707469","id":1116698358,"geo":"MA"},{"colors":"#a8a7a6","id":1117416414,"geo":"MA"},{"colors":"#638287","id":1117268359,"geo":"MA"},{"colors":"#828283","id":1113151170,"geo":"MA"},{"colors":"#a89b91","id":1117678176,"geo":"MA"},{"colors":"#736f71","id":1114899413,"geo":"MA"},{"colors":"#91b990","id":1119954450,"geo":"MA"},{"colors":"#959485","id":1119115913,"geo":"MA"},{"colors":"#5b9099","id":1119115495,"geo":"MA"},{"colors":"#d3d0b4","id":1117519670,"geo":"MA"},{"colors":"#bcbaaf","id":1122555412,"geo":"MA"},{"colors":"#6d7885","id":1113204701,"geo":"MA"},{"colors":"#817481","id":1122524113,"geo":"MA"},{"colors":"#9a9090","id":1117953724,"geo":"MA"},{"colors":"#807a6a","id":1125731243,"geo":"MA"},{"colors":"#8c9293","id":1122935632,"geo":"MA"},{"colors":"#9e9496","id":1118487141,"geo":"MA"},{"colors":"#97908a","id":1125944687,"geo":"MA"},{"colors":"#b3b3b1","id":1122813047,"geo":"MA"},{"colors":"#657a91","id":1123141711,"geo":"MA"},{"colors":"#a9a392","id":1125944712,"geo":"MA"},{"colors":"#655e66","id":1125752864,"geo":"MA"},{"colors":"#486392","id":1126237389,"geo":"MA"},{"colors":"#30717c","id":1126237427,"geo":"MA"},{"colors":"#7da9af","id":1126237433,"geo":"MA"},{"colors":"#72925e","id":1126237411,"geo":"MA"},{"colors":"#818174","id":1126237428,"geo":"MA"},{"colors":"#b2b7b7","id":1126395268,"geo":"MA"},{"colors":"#353e46","id":1126395269,"geo":"MA"},{"colors":"#866e6f","id":1125944690,"geo":"MA"},{"colors":"#877e7f","id":1127926003,"geo":"MA"},{"colors":"#5c6883","id":1126395393,"geo":"MA"},{"colors":"#313b2f","id":1133528350,"geo":"MA"},{"colors":"#918c8a","id":1133828399,"geo":"MA"},{"colors":"#9a9893","id":1134076743,"geo":"MA"},{"colors":"#8f929d","id":1137750725,"geo":"MA"},{"colors":"#3b444b","id":1137659221,"geo":"MA"},{"colors":"#77b9ca","id":1137659402,"geo":"MA"},{"colors":"#a9b5ba","id":1131307564,"geo":"MA"},{"colors":"#afa69c","id":1135464559,"geo":"MA"},{"colors":"#7d968d","id":1136314560,"geo":"MA"},{"colors":"#57776a","id":1139086307,"geo":"MA"},{"colors":"#595458","id":1144153898,"geo":"MA"},{"colors":"#a49884","id":1137750739,"geo":"MA"},{"colors":"#a5b6ba","id":1137750736,"geo":"MA"},{"colors":"#263143","id":1145687772,"geo":"MA"},{"colors":"#4c5871","id":1139092265,"geo":"MA"},{"colors":"#a6a295","id":1157237262,"geo":"MA"},{"colors":"#4b6981","id":1156851625,"geo":"MA"},{"colors":"#1f2627","id":1139082612,"geo":"MA"},{"colors":"#22212e","id":1157307123,"geo":"MA"},{"colors":"#a98c8d","id":1144513782,"geo":"MA"},{"colors":"#8a9289","id":1157253389,"geo":"MA"},{"colors":"#6e85a2","id":1158277105,"geo":"MA"},{"colors":"#bfc6c4","id":1159145241,"geo":"MA"},{"colors":"#6b6465","id":1157307122,"geo":"MA"},{"colors":"#b1a399","id":1162673168,"geo":"MA"},{"colors":"#888f8e","id":1160558542,"geo":"MA"},{"colors":"#5e90a5","id":1135317889,"geo":"MA"},{"colors":"#808f7b","id":1162268075,"geo":"MA"},{"colors":"#8a958a","id":1162673169,"geo":"MA"},{"colors":"#90b998","id":1141583466,"geo":"MA"},{"colors":"#837e7c","id":1160946192,"geo":"MA"},{"colors":"#9e968a","id":1164771432,"geo":"MA"},{"colors":"#86b0bb","id":1178492082,"geo":"MA"},{"colors":"#8b9691","id":1173376422,"geo":"MA"},{"colors":"#85828d","id":1190813133,"geo":"MA"},{"colors":"#7390ab","id":1185424103,"geo":"MA"},{"colors":"#23242b","id":1196902282,"geo":"MA"},{"colors":"#999090","id":1199964183,"geo":"MA"},{"colors":"#1b211e","id":913911223,"geo":"MA"},{"colors":"#222528","id":922150274,"geo":"MA"},{"colors":"#3a3e46","id":916331035,"geo":"MA"},{"colors":"#626767","id":1058735468,"geo":"MA"},{"colors":"#7298ab","id":1164771425,"geo":"MA"},{"colors":"#5f5e56","id":1025392901,"geo":"MA"},{"colors":"#616054","id":1060912783,"geo":"MA"},{"colors":"#292622","id":1063438148,"geo":"MA"},{"colors":"#48524e","id":1049704486,"geo":"MA"},{"colors":"#454e3e","id":1056715857,"geo":"MA"},{"colors":"#545f53","id":1089349754,"geo":"MA"},{"colors":"#929073","id":1162268063,"geo":"MA"},{"colors":"#3d414a","id":1074249608,"geo":"MA"},{"colors":"#191c1a","id":1089755516,"geo":"MA"},{"colors":"#808c78","id":1097852457,"geo":"MA"},{"colors":"#34372b","id":1097852458,"geo":"MA"},{"colors":"#757d7b","id":1102747063,"geo":"MA"},{"colors":"#5b6d72","id":1102747072,"geo":"MA"},{"colors":"#b9c4bb","id":1102747069,"geo":"MA"},{"colors":"#606a74","id":1101064219,"geo":"MA"},{"colors":"#262722","id":1103254376,"geo":"MA"},{"colors":"#818575","id":1102747079,"geo":"MA"},{"colors":"#686353","id":1103679142,"geo":"MA"},{"colors":"#606b58","id":1104661359,"geo":"MA"},{"colors":"#676b62","id":1103679135,"geo":"MA"},{"colors":"#5f6d5e","id":1089349807,"geo":"MA"},{"colors":"#656c61","id":1110642456,"geo":"MA"},{"colors":"#637165","id":1102638483,"geo":"MA"},{"colors":"#4d5648","id":1105088631,"geo":"MA"},{"colors":"#445043","id":1112601061,"geo":"MA"},{"colors":"#676964","id":1115259504,"geo":"MA"},{"colors":"#5b665b","id":1110642535,"geo":"MA"},{"colors":"#434337","id":1141812423,"geo":"MA"},{"colors":"#2d2f2a","id":1157241624,"geo":"MA"},{"colors":"#2e2e25","id":1137325387,"geo":"MA"},{"colors":"#758558","id":1161811413,"geo":"MA"},{"colors":"#56534a","id":1145687785,"geo":"MA"},{"colors":"#454a40","id":1174920827,"geo":"MA"},{"colors":"#24303d","id":1231922207,"geo":"MA"},{"colors":"#434145","id":1211717381,"geo":"MA"},{"colors":"#5c685b","id":1220159700,"geo":"MA"},{"colors":"#453f3b","id":1221870080,"geo":"MA"},{"colors":"#787579","id":1231795763,"geo":"MA"},{"colors":"#838ca1","id":1230956539,"geo":"MA"},{"colors":"#828183","id":1228176631,"geo":"MA"},{"colors":"#8b868a","id":1233441458,"geo":"MA"},{"colors":"#4a4c48","id":1232577087,"geo":"MA"},{"colors":"#6f6e6f","id":1237470153,"geo":"MA"},{"colors":"#6f6e71","id":1255169410,"geo":"MA"},{"colors":"#697173","id":1267835430,"geo":"MA"},{"colors":"#6b6a77","id":1231931443,"geo":"MA"},{"colors":"#576b6c","id":1266855315,"geo":"MA"},{"colors":"#7f7a78","id":1268497511,"geo":"MA"},{"colors":"#70a76e","id":1202969061,"geo":"MA"},{"colors":"#436464","id":1202041122,"geo":"MA"},{"colors":"#7a8379","id":1244092353,"geo":"MA"},{"colors":"#6c694f","id":1220109924,"geo":"MA"},{"colors":"#554d4d","id":1211628561,"geo":"MA"},{"colors":"#9b9993","id":1199964193,"geo":"MA"},{"colors":"#859c98","id":1199964186,"geo":"MA"},{"colors":"#7ca58f","id":1225955893,"geo":"MA"},{"colors":"#2b3339","id":1227021739,"geo":"MA"},{"colors":"#9d9c93","id":1234708235,"geo":"MA"},{"colors":"#716d56","id":1227401209,"geo":"MA"},{"colors":"#bdb1a1","id":1236737941,"geo":"MA"},{"colors":"#cfbfa8","id":1227006259,"geo":"MA"},{"colors":"#627486","id":1235638391,"geo":"MA"},{"colors":"#ada58f","id":1245428566,"geo":"MA"},{"colors":"#29333a","id":1244039725,"geo":"MA"},{"colors":"#7d7f7b","id":1251292151,"geo":"MA"},{"colors":"#6b94b9","id":1245940683,"geo":"MA"},{"colors":"#d2bb95","id":1234708234,"geo":"MA"},{"colors":"#999480","id":1260736406,"geo":"MA"},{"colors":"#8f876a","id":1252499984,"geo":"MA"},{"colors":"#848371","id":1234708232,"geo":"MA"},{"colors":"#665d70","id":1266508747,"geo":"MA"},{"colors":"#7a747d","id":1255164303,"geo":"MA"},{"colors":"#40454f","id":1265629103,"geo":"MA"},{"colors":"#c4b6a0","id":1264684538,"geo":"MA"},{"colors":"#736c61","id":1261927604,"geo":"MA"},{"colors":"#757473","id":1271815331,"geo":"MA"},{"colors":"#859e98","id":1266883867,"geo":"MA"},{"colors":"#98867f","id":1268061661,"geo":"MA"},{"colors":"#77767d","id":1268191822,"geo":"MA"},{"colors":"#b6b6ba","id":1271230104,"geo":"MA"},{"colors":"#70636c","id":1277838631,"geo":"MA"},{"colors":"#6b9a95","id":1268596074,"geo":"MA"},{"colors":"#3f4551","id":1275030106,"geo":"MA"},{"colors":"#1d202d","id":1277837311,"geo":"MA"},{"colors":"#5e6d5c","id":1225556648,"geo":"MA"},{"colors":"#1f211e","id":1240625932,"geo":"MA"},{"colors":"#656c66","id":1235940646,"geo":"MA"},{"colors":"#516649","id":1281008399,"geo":"MA"},{"colors":"#394037","id":1225556666,"geo":"MA"},{"colors":"#96918b","id":1275750723,"geo":"MA"},{"colors":"#79988b","id":1279175553,"geo":"MA"},{"colors":"#706e5f","id":1261927631,"geo":"MA"}]