[{"colors":"#8e8d8f","id":188161596,"geo":"ME"},{"colors":"#8a948d","id":231616654,"geo":"ME"},{"colors":"#7f8180","id":192836907,"geo":"ME"},{"colors":"#655a56","id":273211989,"geo":"ME"},{"colors":"#697b87","id":308444692,"geo":"ME"},{"colors":"#dde0df","id":278131876,"geo":"ME"},{"colors":"#6c7b81","id":142810729,"geo":"ME"},{"colors":"#6c7771","id":345273910,"geo":"ME"},{"colors":"#6f6f71","id":96027316,"geo":"ME"},{"colors":"#777984","id":323298395,"geo":"ME"},{"colors":"#626477","id":354106235,"geo":"ME"},{"colors":"#869bc4","id":362658100,"geo":"ME"},{"colors":"#666c6b","id":366407025,"geo":"ME"},{"colors":"#817e78","id":313628862,"geo":"ME"},{"colors":"#937072","id":414024082,"geo":"ME"},{"colors":"#6c6c69","id":425619569,"geo":"ME"},{"colors":"#5d6076","id":430207506,"geo":"ME"},{"colors":"#8b93a0","id":443275471,"geo":"ME"},{"colors":"#7f8086","id":469896146,"geo":"ME"},{"colors":"#8e807a","id":456205441,"geo":"ME"},{"colors":"#6f6764","id":458241815,"geo":"ME"},{"colors":"#90908e","id":443110579,"geo":"ME"},{"colors":"#445474","id":474782835,"geo":"ME"},{"colors":"#858c80","id":396333369,"geo":"ME"},{"colors":"#858682","id":473294895,"geo":"ME"},{"colors":"#a5aaa8","id":545317631,"geo":"ME"},{"colors":"#6c7480","id":451859473,"geo":"ME"},{"colors":"#628ad0","id":640346161,"geo":"ME"},{"colors":"#3d3d51","id":660590092,"geo":"ME"},{"colors":"#a2a3a2","id":558794883,"geo":"ME"},{"colors":"#73716c","id":526295641,"geo":"ME"},{"colors":"#59616e","id":511304575,"geo":"ME"},{"colors":"#656466","id":732762858,"geo":"ME"},{"colors":"#545257","id":700936177,"geo":"ME"},{"colors":"#5f788b","id":629590261,"geo":"ME"},{"colors":"#898d95","id":594648853,"geo":"ME"},{"colors":"#5f5e75","id":723126715,"geo":"ME"},{"colors":"#616062","id":679503747,"geo":"ME"},{"colors":"#525253","id":700936186,"geo":"ME"},{"colors":"#545764","id":717888110,"geo":"ME"},{"colors":"#8c8a8a","id":733995155,"geo":"ME"},{"colors":"#676c6a","id":741233395,"geo":"ME"},{"colors":"#797a7b","id":741233388,"geo":"ME"},{"colors":"#5d6263","id":746383075,"geo":"ME"},{"colors":"#4f5258","id":741233401,"geo":"ME"},{"colors":"#7b7b7e","id":761619437,"geo":"ME"},{"colors":"#778379","id":763501172,"geo":"ME"},{"colors":"#516959","id":763517589,"geo":"ME"},{"colors":"#504847","id":762663640,"geo":"ME"},{"colors":"#38363f","id":770655191,"geo":"ME"},{"colors":"#605e63","id":763744772,"geo":"ME"},{"colors":"#8f835e","id":773643173,"geo":"ME"},{"colors":"#707170","id":768695647,"geo":"ME"},{"colors":"#9c9486","id":765760957,"geo":"ME"},{"colors":"#7c86b2","id":782245029,"geo":"ME"},{"colors":"#584f5d","id":785892681,"geo":"ME"},{"colors":"#212933","id":750960120,"geo":"ME"},{"colors":"#98a8bd","id":783628284,"geo":"ME"},{"colors":"#606c7d","id":801662188,"geo":"ME"},{"colors":"#b2ada0","id":847594385,"geo":"ME"},{"colors":"#9b9896","id":814438985,"geo":"ME"},{"colors":"#a19f9d","id":851896121,"geo":"ME"},{"colors":"#6e747d","id":853003744,"geo":"ME"},{"colors":"#717678","id":850983234,"geo":"ME"},{"colors":"#a5a09b","id":851348157,"geo":"ME"},{"colors":"#0c122a","id":857245649,"geo":"ME"},{"colors":"#9ca1a8","id":860374686,"geo":"ME"},{"colors":"#8b8d8d","id":816321700,"geo":"ME"},{"colors":"#657e76","id":858148975,"geo":"ME"},{"colors":"#727477","id":891005834,"geo":"ME"},{"colors":"#565669","id":914387103,"geo":"ME"},{"colors":"#c8b29b","id":919973513,"geo":"ME"},{"colors":"#676971","id":849989852,"geo":"ME"},{"colors":"#827d78","id":897756656,"geo":"ME"},{"colors":"#293032","id":954448755,"geo":"ME"},{"colors":"#313039","id":925269964,"geo":"ME"},{"colors":"#736f65","id":960128033,"geo":"ME"},{"colors":"#8c8f7e","id":976500569,"geo":"ME"},{"colors":"#b3b9ad","id":974814712,"geo":"ME"},{"colors":"#365043","id":962413008,"geo":"ME"},{"colors":"#595d78","id":963280220,"geo":"ME"},{"colors":"#675b60","id":971373753,"geo":"ME"},{"colors":"#5e5a5f","id":922307853,"geo":"ME"},{"colors":"#32303b","id":975318115,"geo":"ME"},{"colors":"#556b75","id":899206198,"geo":"ME"},{"colors":"#4c5b70","id":801983688,"geo":"ME"},{"colors":"#7c7d7c","id":941121286,"geo":"ME"},{"colors":"#8e8d8c","id":979399393,"geo":"ME"},{"colors":"#939094","id":987047265,"geo":"ME"},{"colors":"#b58685","id":987024648,"geo":"ME"},{"colors":"#a4a191","id":980224877,"geo":"ME"},{"colors":"#909393","id":1000536831,"geo":"ME"},{"colors":"#535759","id":993437902,"geo":"ME"},{"colors":"#506d71","id":1006659317,"geo":"ME"},{"colors":"#797066","id":984950629,"geo":"ME"},{"colors":"#8d918e","id":1004789567,"geo":"ME"},{"colors":"#7c848c","id":1044570362,"geo":"ME"},{"colors":"#6c7975","id":1021298916,"geo":"ME"},{"colors":"#2a524e","id":1041471021,"geo":"ME"},{"colors":"#878a8a","id":1037829570,"geo":"ME"},{"colors":"#726e6e","id":1074725761,"geo":"ME"},{"colors":"#607186","id":1041471014,"geo":"ME"},{"colors":"#416553","id":1080654745,"geo":"ME"},{"colors":"#6a6f78","id":1071781235,"geo":"ME"},{"colors":"#7d8372","id":1080654755,"geo":"ME"},{"colors":"#535e6c","id":1080654735,"geo":"ME"},{"colors":"#7e8487","id":1079425778,"geo":"ME"},{"colors":"#707466","id":1095196652,"geo":"ME"},{"colors":"#797271","id":1105576441,"geo":"ME"},{"colors":"#b27b7b","id":1091056804,"geo":"ME"},{"colors":"#526c6b","id":1093208945,"geo":"ME"},{"colors":"#9c9380","id":1131853440,"geo":"ME"},{"colors":"#868fa1","id":1143793659,"geo":"ME"},{"colors":"#95a3a1","id":1161832266,"geo":"ME"},{"colors":"#717b6d","id":1123311057,"geo":"ME"},{"colors":"#a99c8b","id":1178128780,"geo":"ME"},{"colors":"#8ea098","id":1190016887,"geo":"ME"},{"colors":"#aba89e","id":1219103019,"geo":"ME"},{"colors":"#8a8888","id":1163747432,"geo":"ME"},{"colors":"#495046","id":1196658221,"geo":"ME"},{"colors":"#2d3041","id":1231190416,"geo":"ME"},{"colors":"#646e71","id":1234159303,"geo":"ME"},{"colors":"#60616b","id":1237980065,"geo":"ME"},{"colors":"#2c3466","id":1241489341,"geo":"ME"},{"colors":"#dee9eb","id":1242400565,"geo":"ME"},{"colors":"#616d80","id":1253644252,"geo":"ME"},{"colors":"#8b8c8d","id":1283709842,"geo":"ME"},{"colors":"#8b8c7c","id":233625445,"geo":"ME"},{"colors":"#6d7b88","id":1247478370,"geo":"ME"},{"colors":"#60ad81","id":29194486,"geo":"ME"},{"colors":"#0a1525","id":231467046,"geo":"ME"},{"colors":"#7f7e83","id":146138527,"geo":"ME"},{"colors":"#747277","id":272361061,"geo":"ME"},{"colors":"#7e8d72","id":192384135,"geo":"ME"},{"colors":"#494642","id":297826541,"geo":"ME"},{"colors":"#464a4f","id":297826536,"geo":"ME"},{"colors":"#8b9394","id":340296945,"geo":"ME"},{"colors":"#5f606a","id":324758200,"geo":"ME"},{"colors":"#446b6a","id":361642162,"geo":"ME"},{"colors":"#99967e","id":379031219,"geo":"ME"},{"colors":"#474c4c","id":397183804,"geo":"ME"},{"colors":"#726e6c","id":404574609,"geo":"ME"},{"colors":"#97a38c","id":395166573,"geo":"ME"},{"colors":"#676f74","id":306561278,"geo":"ME"},{"colors":"#888b88","id":425209146,"geo":"ME"},{"colors":"#73786e","id":443072378,"geo":"ME"},{"colors":"#8b9186","id":443072375,"geo":"ME"},{"colors":"#b0646d","id":403553404,"geo":"ME"},{"colors":"#828275","id":459086960,"geo":"ME"},{"colors":"#66ab7b","id":455395937,"geo":"ME"},{"colors":"#76796d","id":453721216,"geo":"ME"},{"colors":"#797c70","id":356031745,"geo":"ME"},{"colors":"#596072","id":460916312,"geo":"ME"},{"colors":"#6992ad","id":462262469,"geo":"ME"},{"colors":"#5a6974","id":484566188,"geo":"ME"},{"colors":"#8c8b78","id":498874404,"geo":"ME"},{"colors":"#707360","id":475984550,"geo":"ME"},{"colors":"#8a9291","id":514874949,"geo":"ME"},{"colors":"#7e7b6b","id":498362060,"geo":"ME"},{"colors":"#969988","id":497925106,"geo":"ME"},{"colors":"#292f46","id":547180845,"geo":"ME"},{"colors":"#6a7777","id":527125825,"geo":"ME"},{"colors":"#8e987d","id":547104414,"geo":"ME"},{"colors":"#98a9aa","id":516240866,"geo":"ME"},{"colors":"#2f2e28","id":594391463,"geo":"ME"},{"colors":"#999792","id":548430799,"geo":"ME"},{"colors":"#616b3e","id":559835254,"geo":"ME"},{"colors":"#4d5f72","id":625278190,"geo":"ME"},{"colors":"#6e736c","id":643146433,"geo":"ME"},{"colors":"#959e91","id":679051610,"geo":"ME"},{"colors":"#909381","id":753058487,"geo":"ME"},{"colors":"#7d828f","id":749222282,"geo":"ME"},{"colors":"#8a8469","id":704892423,"geo":"ME"},{"colors":"#abaaa4","id":760615223,"geo":"ME"},{"colors":"#818488","id":767400593,"geo":"ME"},{"colors":"#707b71","id":785443498,"geo":"ME"},{"colors":"#596d5e","id":396112942,"geo":"ME"},{"colors":"#707764","id":777275951,"geo":"ME"},{"colors":"#b8b6ad","id":786029041,"geo":"ME"},{"colors":"#6f755e","id":786029042,"geo":"ME"},{"colors":"#0e1a3f","id":786265684,"geo":"ME"},{"colors":"#716e61","id":785848883,"geo":"ME"},{"colors":"#7a8578","id":791111215,"geo":"ME"},{"colors":"#111634","id":786265675,"geo":"ME"},{"colors":"#8a817b","id":789271529,"geo":"ME"},{"colors":"#5e6d7d","id":792718890,"geo":"ME"},{"colors":"#948d87","id":808840932,"geo":"ME"},{"colors":"#74796b","id":793225658,"geo":"ME"},{"colors":"#aea292","id":806193224,"geo":"ME"},{"colors":"#858c7e","id":796510557,"geo":"ME"},{"colors":"#717a69","id":813500839,"geo":"ME"},{"colors":"#8e9652","id":812674358,"geo":"ME"},{"colors":"#706b6b","id":814305010,"geo":"ME"},{"colors":"#7e7ea1","id":809285343,"geo":"ME"},{"colors":"#878c73","id":815504675,"geo":"ME"},{"colors":"#666c63","id":816879396,"geo":"ME"},{"colors":"#77757e","id":816586474,"geo":"ME"},{"colors":"#5d595f","id":816321702,"geo":"ME"},{"colors":"#8b867b","id":822847402,"geo":"ME"},{"colors":"#afa89d","id":846209237,"geo":"ME"},{"colors":"#979a95","id":815544628,"geo":"ME"},{"colors":"#65675f","id":842187228,"geo":"ME"},{"colors":"#7b7d70","id":816481513,"geo":"ME"},{"colors":"#91999b","id":858093047,"geo":"ME"},{"colors":"#c8c5be","id":858190060,"geo":"ME"},{"colors":"#55574f","id":877913138,"geo":"ME"},{"colors":"#444859","id":849612615,"geo":"ME"},{"colors":"#6b705f","id":846592708,"geo":"ME"},{"colors":"#8e9791","id":863104656,"geo":"ME"},{"colors":"#73786d","id":877981951,"geo":"ME"},{"colors":"#667948","id":860243414,"geo":"ME"},{"colors":"#3c403d","id":1281984531,"geo":"ME"},{"colors":"#818987","id":890164449,"geo":"ME"},{"colors":"#636061","id":880815013,"geo":"ME"},{"colors":"#43544b","id":872045881,"geo":"ME"},{"colors":"#49403d","id":930455535,"geo":"ME"},{"colors":"#83907a","id":963666399,"geo":"ME"},{"colors":"#5d6257","id":862889786,"geo":"ME"},{"colors":"#848976","id":971377658,"geo":"ME"},{"colors":"#7b5a4e","id":986487202,"geo":"ME"},{"colors":"#8b9153","id":988200836,"geo":"ME"},{"colors":"#9b948d","id":917642092,"geo":"ME"},{"colors":"#848875","id":920208215,"geo":"ME"},{"colors":"#54505a","id":991963376,"geo":"ME"},{"colors":"#505954","id":1013045282,"geo":"ME"},{"colors":"#b6afa0","id":992259445,"geo":"ME"},{"colors":"#60695e","id":1001812198,"geo":"ME"},{"colors":"#787779","id":1034907397,"geo":"ME"},{"colors":"#977979","id":1032765458,"geo":"ME"},{"colors":"#798476","id":1012136558,"geo":"ME"},{"colors":"#5f6d76","id":1037002034,"geo":"ME"},{"colors":"#4f5664","id":1018740661,"geo":"ME"},{"colors":"#7c7e9c","id":976508350,"geo":"ME"},{"colors":"#414b67","id":1044743969,"geo":"ME"},{"colors":"#211d22","id":1001215695,"geo":"ME"},{"colors":"#898884","id":1046906145,"geo":"ME"},{"colors":"#7f8cb2","id":1050162536,"geo":"ME"},{"colors":"#516264","id":1052704881,"geo":"ME"},{"colors":"#b8a889","id":1077695661,"geo":"ME"},{"colors":"#3f515a","id":1041471027,"geo":"ME"},{"colors":"#1b2028","id":1081867066,"geo":"ME"},{"colors":"#5b8da1","id":1072619910,"geo":"ME"},{"colors":"#1f3a4b","id":1082934270,"geo":"ME"},{"colors":"#767c6f","id":1105106274,"geo":"ME"},{"colors":"#7d8171","id":1164260407,"geo":"ME"},{"colors":"#5e6562","id":1105079003,"geo":"ME"},{"colors":"#47584d","id":1178786301,"geo":"ME"},{"colors":"#73796e","id":1136579875,"geo":"ME"},{"colors":"#838771","id":1191311552,"geo":"ME"},{"colors":"#525b6c","id":1091735692,"geo":"ME"},{"colors":"#a1a394","id":1190020027,"geo":"ME"},{"colors":"#152139","id":1207019076,"geo":"ME"},{"colors":"#87907f","id":1208040342,"geo":"ME"},{"colors":"#606b5b","id":1101723351,"geo":"ME"},{"colors":"#909485","id":1219889406,"geo":"ME"},{"colors":"#82877b","id":1219889408,"geo":"ME"},{"colors":"#cbb89d","id":1230709893,"geo":"ME"},{"colors":"#67675e","id":1237980080,"geo":"ME"},{"colors":"#7d8385","id":1241554108,"geo":"ME"},{"colors":"#646d70","id":1199667472,"geo":"ME"},{"colors":"#8b958f","id":1274464208,"geo":"ME"},{"colors":"#716d68","id":1281336520,"geo":"ME"},{"colors":"#b8b09e","id":1245031033,"geo":"ME"},{"colors":"#a0a5ad","id":1267467089,"geo":"ME"},{"colors":"#4d5f6e","id":1169198622,"geo":"ME"},{"colors":"#72a680","id":1238926780,"geo":"ME"},{"colors":"#5c625c","id":425042407,"geo":"ME"},{"colors":"#78786a","id":1203812849,"geo":"ME"},{"colors":"#656d5f","id":777275981,"geo":"ME"},{"colors":"#767264","id":740733197,"geo":"ME"},{"colors":"#7e837b","id":425408622,"geo":"ME"},{"colors":"#7d7b84","id":1255426225,"geo":"ME"},{"colors":"#41483b","id":777275946,"geo":"ME"},{"colors":"#676e63","id":785590080,"geo":"ME"},{"colors":"#869091","id":789332427,"geo":"ME"},{"colors":"#3a3f37","id":785335799,"geo":"ME"},{"colors":"#637068","id":785443493,"geo":"ME"},{"colors":"#414834","id":917900402,"geo":"ME"},{"colors":"#5a5d5d","id":859808269,"geo":"ME"},{"colors":"#8b9494","id":794541673,"geo":"ME"},{"colors":"#58615c","id":956425876,"geo":"ME"},{"colors":"#5a6956","id":1001812199,"geo":"ME"},{"colors":"#30382c","id":1050098684,"geo":"ME"},{"colors":"#252629","id":1084394044,"geo":"ME"},{"colors":"#5f6c5e","id":1001812200,"geo":"ME"},{"colors":"#3f4236","id":1101756012,"geo":"ME"},{"colors":"#647c69","id":1146080267,"geo":"ME"},{"colors":"#393f31","id":1113194529,"geo":"ME"},{"colors":"#50553f","id":1185577460,"geo":"ME"},{"colors":"#41423c","id":1137322622,"geo":"ME"},{"colors":"#565f54","id":1237981259,"geo":"ME"},{"colors":"#484a4d","id":1199667838,"geo":"ME"},{"colors":"#5f675b","id":1101724196,"geo":"ME"},{"colors":"#6e796b","id":1244599242,"geo":"ME"},{"colors":"#3f4535","id":1186868512,"geo":"ME"},{"colors":"#656a5f","id":1281973765,"geo":"ME"}]